{"Gone Girl": [[23, "Se7en", 831.75], [51, "The Prestige", 816.25], [71, "Oldboy", 816.0], [116, "Chinatown", 815.75], [140, "El secreto de sus ojos", 815.75], [165, "The Sixth Sense", 815.5], [5, "Pulp Fiction", 722.5], [24, "The Usual Suspects", 721.75], [25, "The Silence of the Lambs", 721.5], [28, "L\u00e9on", 721.5]], "Tonari no Totoro": [[243, "Beauty and the Beast", 455.25], [37, "Sen to Chihiro no Kamikakushi", 376.5], [72, "Mononoke-hime", 376.0], [147, "Hauru no ugoku shiro", 375.5], [26, "It's a Wonderful Life", 361.75], [152, "How to Train Your Dragon", 360.5], [190, "The Wizard of Oz", 360.25], [201, "Kaze no tani no Naushika", 280.5], [231, "Tenk\u00fb no shiro Rapyuta", 280.25], [9, "The Lord of the Rings: The Return of the King", 267.25]], "Swades: We, the People": [[213, "Lagaan: Once Upon a Time in India", 220.75], [1, "The Shawshank Redemption", 208.25], [2, "The Godfather", 208.0], [3, "The Godfather: Part II", 207.75], [5, "Pulp Fiction", 207.5], [7, "Schindler's List", 207.25], [8, "12 Angry Men", 207.25], [10, "Fight Club", 207.25], [15, "Forrest Gump", 207.0], [16, "One Flew Over the Cuckoo's Nest", 207.0]], "Platoon": [[30, "Casablanca", 781.5], [35, "Saving Private Ryan", 781.5], [42, "The Pianist", 781.25], [45, "Apocalypse Now", 781.25], [52, "The Great Dictator", 781.25], [59, "Paths of Glory", 781.25], [70, "Das Boot", 781.25], [73, "Hotaru no haka", 781.25], [87, "Full Metal Jacket", 781.0], [105, "Inglourious Basterds", 780.75]], "The Great Escape": [[7, "Schindler's List", 542.25], [56, "The Lion King", 541.25], [70, "Das Boot", 541.25], [83, "Lawrence of Arabia", 541.0], [103, "The Treasure of the Sierra Madre", 541.0], [105, "Inglourious Basterds", 540.75], [117, "Up", 540.75], [118, "Downfall", 540.75], [126, "The Bridge on the River Kwai", 540.75], [157, "Judgment at Nuremberg", 540.75]], "Life of Brian": [[92, "Monty Python and the Holy Grail", 826.0], [29, "La vita \u00e8 bella", 806.5], [34, "City Lights", 806.5], [38, "The Intouchables", 806.5], [39, "Modern Times", 806.5], [46, "Dr. Strangelove or: How I Learned to Stop Worrying and Love the Bomb", 806.25], [49, "Back to the Future", 806.25], [52, "The Great Dictator", 806.25], [65, "Am\u00e9lie", 806.25], [124, "3 Idiots", 806.25]], "Hotel Rwanda": [[157, "Judgment at Nuremberg", 425.75], [7, "Schindler's List", 332.25], [30, "Casablanca", 331.5], [35, "Saving Private Ryan", 331.5], [42, "The Pianist", 331.25], [45, "Apocalypse Now", 331.25], [52, "The Great Dictator", 331.25], [59, "Paths of Glory", 331.25], [70, "Das Boot", 331.25], [73, "Hotaru no haka", 331.25]], "Stand by Me": [[56, "The Lion King", 961.25], [70, "Das Boot", 961.25], [83, "Lawrence of Arabia", 961.0], [103, "The Treasure of the Sierra Madre", 961.0], [105, "Inglourious Basterds", 960.75], [117, "Up", 960.75], [119, "The Great Escape", 960.75], [126, "The Bridge on the River Kwai", 960.75], [161, "The Wages of Fear", 960.75], [213, "Lagaan: Once Upon a Time in India", 960.75]], "The Raiders of the Lost Ark": [[106, "Indiana Jones and the Final Crusade", 895.75], [13, "Star Wars: Episode V - The Empire Strikes Back", 882.0], [20, "Star Wars", 881.75], [74, "Star Wars: Episode VI - Return of the Jedi", 881.0], [4, "The Dark Knight", 872.5], [54, "The Dark Knight Rises", 871.5], [63, "Aliens", 871.0], [94, "Guardians of the Galaxy", 871.0], [103, "The Treasure of the Sierra Madre", 871.0], [109, "Batman Begins", 870.75]], "Once Upon a Time in the West": [[6, "The Good, the Bad and the Ugly", 312.5], [99, "For a Few Dollars More", 310.75], [230, "For a Fistful of Dollars", 310.25], [55, "Django Unchained", 296.25], [112, "Unforgiven", 295.75], [170, "Butch Cassidy and the Sundance Kid", 295.5], [205, "High Noon", 295.25], [76, "Once Upon a Time in America", 216.0], [8, "12 Angry Men", 212.25], [189, "The Grapes of Wrath", 210.5]], "El secreto de sus ojos": [[23, "Se7en", 426.75], [51, "The Prestige", 426.25], [71, "Oldboy", 426.0], [84, "Gone Girl", 426.0], [116, "Chinatown", 425.75], [165, "The Sixth Sense", 425.5], [5, "Pulp Fiction", 332.5], [24, "The Usual Suspects", 331.75], [25, "The Silence of the Lambs", 331.5], [28, "L\u00e9on", 331.5]], "La haine": [[1, "The Shawshank Redemption", 478.25], [2, "The Godfather", 478.0], [3, "The Godfather: Part II", 477.75], [5, "Pulp Fiction", 477.5], [7, "Schindler's List", 477.25], [8, "12 Angry Men", 477.25], [10, "Fight Club", 477.25], [15, "Forrest Gump", 477.0], [16, "One Flew Over the Cuckoo's Nest", 477.0], [18, "Goodfellas", 476.75]], "The Best Years of Our Lives": [[30, "Casablanca", 546.5], [159, "Gone with the Wind", 545.5], [234, "Roman Holiday", 465.25], [15, "Forrest Gump", 452.0], [29, "La vita \u00e8 bella", 451.5], [34, "City Lights", 451.5], [35, "Saving Private Ryan", 451.5], [42, "The Pianist", 451.25], [45, "Apocalypse Now", 451.25], [52, "The Great Dictator", 451.25]], "A Beautiful Mind": [[154, "Rush", 405.5], [7, "Schindler's List", 392.25], [18, "Goodfellas", 391.75], [38, "The Intouchables", 391.5], [42, "The Pianist", 391.25], [81, "Braveheart", 391.0], [83, "Lawrence of Arabia", 391.0], [91, "Amadeus", 391.0], [113, "Raging Bull", 390.75], [118, "Downfall", 390.75]], "Blade Runner": [[14, "Inception", 842.0], [40, "T2: Judgment Day", 841.25], [207, "Twelve Monkeys", 840.25], [240, "Jurassic Park", 840.0], [50, "Alien", 761.25], [5, "Pulp Fiction", 747.5], [12, "Interstellar", 747.5], [19, "The Matrix", 746.75], [23, "Se7en", 746.75], [24, "The Usual Suspects", 746.75]], "The Princess Bride": [[37, "Sen to Chihiro no Kamikakushi", 331.5], [49, "Back to the Future", 331.25], [68, "Toy Story 3", 331.0], [92, "Monty Python and the Holy Grail", 331.0], [101, "The Kid", 331.0], [110, "Toy Story", 330.75], [133, "The Gold Rush", 330.75], [137, "The General", 330.75], [147, "Hauru no ugoku shiro", 330.5], [152, "How to Train Your Dragon", 330.5]], "Metropolis": [[75, "A Clockwork Orange", 901.0], [85, "Eternal Sunshine of the Spotless Mind", 901.0], [206, "Stalker", 900.5], [199, "Donnie Darko", 900.25], [238, "Her", 900.25], [67, "M", 821.25], [1, "The Shawshank Redemption", 808.25], [2, "The Godfather", 808.0], [3, "The Godfather: Part II", 807.75], [5, "Pulp Fiction", 807.5]], "Stalag 17": [[52, "The Great Dictator", 486.25], [244, "Underground", 485.5], [98, "The Apartment", 406.0], [126, "The Bridge on the River Kwai", 400.75], [29, "La vita \u00e8 bella", 391.5], [30, "Casablanca", 391.5], [34, "City Lights", 391.5], [35, "Saving Private Ryan", 391.5], [38, "The Intouchables", 391.5], [42, "The Pianist", 391.25]], "Witness for the Prosecution": [[95, "Rash\u00f4mon", 456.0], [97, "L.A. Confidential", 455.75], [228, "Salinui chueok", 455.25], [78, "Double Indemnity", 376.0], [1, "The Shawshank Redemption", 363.25], [2, "The Godfather", 363.0], [3, "The Godfather: Part II", 362.75], [5, "Pulp Fiction", 362.5], [18, "Goodfellas", 361.75], [22, "City of God", 361.75]], "Indiana Jones and the Final Crusade": [[31, "The Raiders of the Lost Ark", 926.5], [13, "Star Wars: Episode V - The Empire Strikes Back", 912.0], [20, "Star Wars", 911.75], [74, "Star Wars: Episode VI - Return of the Jedi", 911.0], [4, "The Dark Knight", 902.5], [54, "The Dark Knight Rises", 901.5], [63, "Aliens", 901.0], [94, "Guardians of the Galaxy", 901.0], [103, "The Treasure of the Sierra Madre", 901.0], [109, "Batman Begins", 900.75]], "The Avengers": [[63, "Aliens", 756.0], [94, "Guardians of the Galaxy", 756.0], [183, "X-Men: Days of Future Past", 755.5], [4, "The Dark Knight", 662.5], [12, "Interstellar", 662.5], [13, "Star Wars: Episode V - The Empire Strikes Back", 662.0], [14, "Inception", 662.0], [19, "The Matrix", 661.75], [20, "Star Wars", 661.75], [31, "The Raiders of the Lost Ark", 661.5]], "The Graduate": [[29, "La vita \u00e8 bella", 1476.5], [34, "City Lights", 1476.5], [98, "The Apartment", 1476.0], [178, "Annie Hall", 1475.5], [234, "Roman Holiday", 1475.25], [15, "Forrest Gump", 1382.0], [30, "Casablanca", 1381.5], [38, "The Intouchables", 1381.5], [52, "The Great Dictator", 1381.25], [65, "Am\u00e9lie", 1381.25]], "The Killing": [[177, "Touch of Evil", 335.5], [202, "Strangers on a Train", 335.25], [219, "The Night of the Hunter", 335.25], [5, "Pulp Fiction", 242.5], [24, "The Usual Suspects", 241.75], [25, "The Silence of the Lambs", 241.5], [28, "L\u00e9on", 241.5], [47, "The Departed", 241.25], [67, "M", 241.25], [78, "Double Indemnity", 241.0]], "Kill Bill: Vol. 1": [[125, "Heat", 660.75], [197, "The Bourne Ultimatum", 660.25], [5, "Pulp Fiction", 592.5], [79, "Reservoir Dogs", 581.0], [1, "The Shawshank Redemption", 568.25], [2, "The Godfather", 568.0], [3, "The Godfather: Part II", 567.75], [4, "The Dark Knight", 567.5], [13, "Star Wars: Episode V - The Empire Strikes Back", 567.0], [14, "Inception", 567.0]], "City Lights": [[29, "La vita \u00e8 bella", 606.5], [98, "The Apartment", 606.0], [178, "Annie Hall", 605.5], [234, "Roman Holiday", 605.25], [235, "The Graduate", 605.25], [52, "The Great Dictator", 536.25], [101, "The Kid", 536.0], [15, "Forrest Gump", 512.0], [30, "Casablanca", 511.5], [38, "The Intouchables", 511.5]], "The Shining": [[33, "Psycho", 656.5], [50, "Alien", 656.25], [166, "The Thing", 655.5], [179, "Les diaboliques", 655.5], [46, "Dr. Strangelove or: How I Learned to Stop Worrying and Love the Bomb", 576.25], [59, "Paths of Glory", 576.25], [75, "A Clockwork Orange", 576.0], [87, "Full Metal Jacket", 576.0], [102, "2001: A Space Odyssey", 575.75], [226, "Barry Lyndon", 575.25]], "Citizen Kane": [[23, "Se7en", 541.75], [51, "The Prestige", 541.25], [86, "Witness for the Prosecution", 541.25], [71, "Oldboy", 541.0], [84, "Gone Girl", 541.0], [95, "Rash\u00f4mon", 541.0], [97, "L.A. Confidential", 540.75], [116, "Chinatown", 540.75], [140, "El secreto de sus ojos", 540.75], [158, "The Maltese Falcon", 540.5]], "Salinui chueok": [[86, "Witness for the Prosecution", 846.25], [95, "Rash\u00f4mon", 846.0], [97, "L.A. Confidential", 845.75], [1, "The Shawshank Redemption", 753.25], [2, "The Godfather", 753.0], [3, "The Godfather: Part II", 752.75], [5, "Pulp Fiction", 752.5], [18, "Goodfellas", 751.75], [22, "City of God", 751.75], [23, "Se7en", 751.75]], "Donnie Darko": [[23, "Se7en", 481.75], [51, "The Prestige", 481.25], [86, "Witness for the Prosecution", 481.25], [64, "Citizen Kane", 481.0], [71, "Oldboy", 481.0], [75, "A Clockwork Orange", 481.0], [84, "Gone Girl", 481.0], [85, "Eternal Sunshine of the Spotless Mind", 481.0], [95, "Rash\u00f4mon", 481.0], [97, "L.A. Confidential", 480.75]], "Inception": [[40, "T2: Judgment Day", 486.25], [19, "The Matrix", 391.75], [63, "Aliens", 391.0], [94, "Guardians of the Galaxy", 391.0], [120, "Die Hard", 390.75], [138, "Blade Runner", 390.5], [146, "V for Vendetta", 390.5], [183, "X-Men: Days of Future Past", 390.5], [194, "The Avengers", 390.5], [197, "The Bourne Ultimatum", 390.25]], "The Gold Rush": [[49, "Back to the Future", 541.25], [68, "Toy Story 3", 541.0], [92, "Monty Python and the Holy Grail", 541.0], [110, "Toy Story", 540.75], [137, "The General", 540.75], [167, "Finding Nemo", 540.5], [182, "The Princess Bride", 540.5], [224, "Monsters, Inc.", 540.25], [34, "City Lights", 471.5], [39, "Modern Times", 471.5]], "The Maltese Falcon": [[229, "The Big Sleep", 430.25], [23, "Se7en", 421.75], [44, "Sunset Blvd.", 421.5], [51, "The Prestige", 421.25], [86, "Witness for the Prosecution", 421.25], [64, "Citizen Kane", 421.0], [71, "Oldboy", 421.0], [78, "Double Indemnity", 421.0], [84, "Gone Girl", 421.0], [95, "Rash\u00f4mon", 421.0]], "The Grand Budapest Hotel": [[29, "La vita \u00e8 bella", 266.5], [34, "City Lights", 266.5], [38, "The Intouchables", 266.5], [39, "Modern Times", 266.5], [46, "Dr. Strangelove or: How I Learned to Stop Worrying and Love the Bomb", 266.25], [49, "Back to the Future", 266.25], [52, "The Great Dictator", 266.25], [65, "Am\u00e9lie", 266.25], [124, "3 Idiots", 266.25], [156, "Dil Chahta Hai", 266.25]], "It Happened One Night": [[29, "La vita \u00e8 bella", 991.5], [34, "City Lights", 991.5], [65, "Am\u00e9lie", 991.25], [88, "Singin' in the Rain", 991.0], [98, "The Apartment", 991.0], [178, "Annie Hall", 990.5], [234, "Roman Holiday", 990.25], [235, "The Graduate", 990.25], [159, "Gone with the Wind", 905.5], [15, "Forrest Gump", 897.0]], "The Terminator": [[40, "T2: Judgment Day", 726.25], [63, "Aliens", 716.0], [14, "Inception", 692.0], [19, "The Matrix", 691.75], [94, "Guardians of the Galaxy", 691.0], [183, "X-Men: Days of Future Past", 690.5], [194, "The Avengers", 690.5], [4, "The Dark Knight", 597.5], [12, "Interstellar", 597.5], [13, "Star Wars: Episode V - The Empire Strikes Back", 597.0]], "The Wizard of Oz": [[9, "The Lord of the Rings: The Return of the King", 452.25], [11, "The Lord of the Rings: The Fellowship of the Ring", 452.0], [13, "Star Wars: Episode V - The Empire Strikes Back", 452.0], [17, "The Lord of the Rings: The Two Towers", 452.0], [20, "Star Wars", 451.75], [26, "It's a Wonderful Life", 451.75], [37, "Sen to Chihiro no Kamikakushi", 451.5], [72, "Mononoke-hime", 451.0], [74, "Star Wars: Episode VI - Return of the Jedi", 451.0], [92, "Monty Python and the Holy Grail", 451.0]], "Yip Man": [[81, "Braveheart", 366.0], [154, "Rush", 365.5], [7, "Schindler's List", 272.25], [18, "Goodfellas", 271.75], [35, "Saving Private Ryan", 271.5], [38, "The Intouchables", 271.5], [42, "The Pianist", 271.25], [48, "Gladiator", 271.25], [83, "Lawrence of Arabia", 271.0], [91, "Amadeus", 271.0]], "Ben-Hur": [[126, "The Bridge on the River Kwai", 580.75], [56, "The Lion King", 571.25], [70, "Das Boot", 571.25], [83, "Lawrence of Arabia", 571.0], [103, "The Treasure of the Sierra Madre", 571.0], [105, "Inglourious Basterds", 570.75], [117, "Up", 570.75], [119, "The Great Escape", 570.75], [161, "The Wages of Fear", 570.75], [213, "Lagaan: Once Upon a Time in India", 570.75]], "Back to the Future": [[12, "Interstellar", 1142.5], [63, "Aliens", 1141.0], [68, "Toy Story 3", 1141.0], [92, "Monty Python and the Holy Grail", 1141.0], [94, "Guardians of the Galaxy", 1141.0], [110, "Toy Story", 1140.75], [133, "The Gold Rush", 1140.75], [137, "The General", 1140.75], [167, "Finding Nemo", 1140.5], [182, "The Princess Bride", 1140.5]], "Gone with the Wind": [[30, "Casablanca", 306.5], [195, "The Best Years of Our Lives", 305.5], [15, "Forrest Gump", 212.0], [29, "La vita \u00e8 bella", 211.5], [34, "City Lights", 211.5], [35, "Saving Private Ryan", 211.5], [42, "The Pianist", 211.25], [45, "Apocalypse Now", 211.25], [52, "The Great Dictator", 211.25], [59, "Paths of Glory", 211.25]], "Am\u00e9lie": [[29, "La vita \u00e8 bella", 511.5], [34, "City Lights", 511.5], [88, "Singin' in the Rain", 511.0], [98, "The Apartment", 511.0], [149, "It Happened One Night", 510.75], [178, "Annie Hall", 510.5], [234, "Roman Holiday", 510.25], [235, "The Graduate", 510.25], [15, "Forrest Gump", 417.0], [30, "Casablanca", 416.5]], "Les diaboliques": [[33, "Psycho", 936.5], [23, "Se7en", 841.75], [36, "Rear Window", 841.5], [41, "Memento", 841.25], [51, "The Prestige", 841.25], [62, "North by Northwest", 841.25], [66, "Vertigo", 841.0], [71, "Oldboy", 841.0], [84, "Gone Girl", 841.0], [104, "The Third Man", 841.0]], "American History X": [[1, "The Shawshank Redemption", 333.25], [2, "The Godfather", 333.0], [3, "The Godfather: Part II", 332.75], [5, "Pulp Fiction", 332.5], [18, "Goodfellas", 331.75], [22, "City of God", 331.75], [24, "The Usual Suspects", 331.75], [25, "The Silence of the Lambs", 331.5], [28, "L\u00e9on", 331.5], [43, "The Green Mile", 331.25]], "Taxi Driver": [[18, "Goodfellas", 566.75], [142, "Casino", 565.5], [47, "The Departed", 556.25], [3, "The Godfather: Part II", 552.75], [25, "The Silence of the Lambs", 551.5], [76, "Once Upon a Time in America", 551.0], [125, "Heat", 550.75], [1, "The Shawshank Redemption", 543.25], [2, "The Godfather", 543.0], [5, "Pulp Fiction", 542.5]], "The Night of the Hunter": [[177, "Touch of Evil", 395.5], [202, "Strangers on a Train", 395.25], [248, "The Killing", 395.25], [5, "Pulp Fiction", 302.5], [24, "The Usual Suspects", 301.75], [25, "The Silence of the Lambs", 301.5], [28, "L\u00e9on", 301.5], [47, "The Departed", 301.25], [67, "M", 301.25], [78, "Double Indemnity", 301.0]], "The Silence of the Lambs": [[5, "Pulp Fiction", 577.5], [24, "The Usual Suspects", 576.75], [28, "L\u00e9on", 576.5], [47, "The Departed", 576.25], [67, "M", 576.25], [153, "Fargo", 575.5], [168, "No Country for Old Men", 575.5], [245, "Rope", 575.25], [77, "Taxi Driver", 491.0], [1, "The Shawshank Redemption", 483.25]], "Tenk\u00fb no shiro Rapyuta": [[201, "Kaze no tani no Naushika", 530.5], [37, "Sen to Chihiro no Kamikakushi", 436.5], [72, "Mononoke-hime", 436.0], [147, "Hauru no ugoku shiro", 435.5], [4, "The Dark Knight", 422.5], [13, "Star Wars: Episode V - The Empire Strikes Back", 422.0], [20, "Star Wars", 421.75], [31, "The Raiders of the Lost Ark", 421.5], [54, "The Dark Knight Rises", 421.5], [56, "The Lion King", 421.25]], "Taare Zameen Par": [[26, "It's a Wonderful Life", 841.75], [101, "The Kid", 841.0], [191, "Hachi: A Dog's Tale", 840.5], [124, "3 Idiots", 756.25], [151, "Rang De Basanti", 756.25], [156, "Dil Chahta Hai", 756.25], [213, "Lagaan: Once Upon a Time in India", 755.75], [1, "The Shawshank Redemption", 748.25], [2, "The Godfather", 748.0], [3, "The Godfather: Part II", 747.75]], "Lock, Stock and Two Smoking Barrels": [[93, "Snatch.", 735.75], [90, "The Sting", 721.0], [128, "The Wolf of Wall Street", 720.75], [143, "The Big Lebowski", 720.5], [246, "Crna macka, beli macor", 720.5], [1, "The Shawshank Redemption", 628.25], [2, "The Godfather", 628.0], [3, "The Godfather: Part II", 627.75], [5, "Pulp Fiction", 627.5], [18, "Goodfellas", 626.75]], "Pan's Labyrinth": [[26, "It's a Wonderful Life", 241.75], [30, "Casablanca", 241.5], [35, "Saving Private Ryan", 241.5], [42, "The Pianist", 241.25], [43, "The Green Mile", 241.25], [45, "Apocalypse Now", 241.25], [52, "The Great Dictator", 241.25], [59, "Paths of Glory", 241.25], [70, "Das Boot", 241.25], [73, "Hotaru no haka", 241.25]], "12 Years a Slave": [[7, "Schindler's List", 577.25], [118, "Downfall", 575.75], [193, "In the Name of the Father", 575.25], [200, "Gandhi", 575.25], [209, "The King's Speech", 575.25], [18, "Goodfellas", 481.75], [38, "The Intouchables", 481.5], [42, "The Pianist", 481.25], [81, "Braveheart", 481.0], [83, "Lawrence of Arabia", 481.0]], "Rash\u00f4mon": [[86, "Witness for the Prosecution", 426.25], [97, "L.A. Confidential", 425.75], [228, "Salinui chueok", 425.25], [1, "The Shawshank Redemption", 333.25], [2, "The Godfather", 333.0], [3, "The Godfather: Part II", 332.75], [5, "Pulp Fiction", 332.5], [18, "Goodfellas", 331.75], [22, "City of God", 331.75], [23, "Se7en", 331.75]], "Casablanca": [[159, "Gone with the Wind", 455.5], [195, "The Best Years of Our Lives", 455.5], [208, "Notorious", 370.25], [15, "Forrest Gump", 362.0], [29, "La vita \u00e8 bella", 361.5], [34, "City Lights", 361.5], [35, "Saving Private Ryan", 361.5], [42, "The Pianist", 361.25], [45, "Apocalypse Now", 361.25], [52, "The Great Dictator", 361.25]], "The Intouchables": [[7, "Schindler's List", 302.25], [18, "Goodfellas", 301.75], [29, "La vita \u00e8 bella", 301.5], [34, "City Lights", 301.5], [42, "The Pianist", 301.25], [52, "The Great Dictator", 301.25], [124, "3 Idiots", 301.25], [156, "Dil Chahta Hai", 301.25], [81, "Braveheart", 301.0], [83, "Lawrence of Arabia", 301.0]], "The King's Speech": [[7, "Schindler's List", 607.25], [118, "Downfall", 605.75], [173, "12 Years a Slave", 605.5], [193, "In the Name of the Father", 605.25], [200, "Gandhi", 605.25], [18, "Goodfellas", 511.75], [38, "The Intouchables", 511.5], [42, "The Pianist", 511.25], [81, "Braveheart", 511.0], [83, "Lawrence of Arabia", 511.0]], "Ran": [[35, "Saving Private Ryan", 456.5], [108, "Yojimbo", 386.0], [30, "Casablanca", 361.5], [42, "The Pianist", 361.25], [45, "Apocalypse Now", 361.25], [48, "Gladiator", 361.25], [52, "The Great Dictator", 361.25], [59, "Paths of Glory", 361.25], [70, "Das Boot", 361.25], [73, "Hotaru no haka", 361.25]], "Rear Window": [[66, "Vertigo", 296.0], [33, "Psycho", 286.5], [62, "North by Northwest", 286.25], [144, "Rebecca", 285.5], [23, "Se7en", 271.75], [41, "Memento", 271.25], [51, "The Prestige", 271.25], [71, "Oldboy", 271.0], [84, "Gone Girl", 271.0], [104, "The Third Man", 271.0]], "Aliens": [[94, "Guardians of the Galaxy", 366.0], [183, "X-Men: Days of Future Past", 365.5], [194, "The Avengers", 365.5], [211, "The Terminator", 295.25], [40, "T2: Judgment Day", 286.25], [4, "The Dark Knight", 272.5], [12, "Interstellar", 272.5], [13, "Star Wars: Episode V - The Empire Strikes Back", 272.0], [14, "Inception", 272.0], [19, "The Matrix", 271.75]], "Fanny och Alexander": [[130, "Det sjunde inseglet", 400.75], [134, "Smultronst\u00e4llet", 400.75], [196, "Persona", 400.5], [1, "The Shawshank Redemption", 388.25], [2, "The Godfather", 388.0], [3, "The Godfather: Part II", 387.75], [5, "Pulp Fiction", 387.5], [7, "Schindler's List", 387.25], [8, "12 Angry Men", 387.25], [10, "Fight Club", 387.25]], "Lawrence of Arabia": [[160, "Into the Wild", 365.5], [126, "The Bridge on the River Kwai", 295.75], [7, "Schindler's List", 272.25], [18, "Goodfellas", 271.75], [38, "The Intouchables", 271.5], [42, "The Pianist", 271.25], [56, "The Lion King", 271.25], [70, "Das Boot", 271.25], [81, "Braveheart", 271.0], [91, "Amadeus", 271.0]], "Requiem for a Dream": [[162, "A Beautiful Mind", 245.5], [1, "The Shawshank Redemption", 238.25], [2, "The Godfather", 238.0], [3, "The Godfather: Part II", 237.75], [5, "Pulp Fiction", 237.5], [7, "Schindler's List", 237.25], [8, "12 Angry Men", 237.25], [10, "Fight Club", 237.25], [15, "Forrest Gump", 237.0], [16, "One Flew Over the Cuckoo's Nest", 237.0]], "The Sixth Sense": [[23, "Se7en", 486.75], [51, "The Prestige", 486.25], [71, "Oldboy", 486.0], [84, "Gone Girl", 486.0], [116, "Chinatown", 485.75], [140, "El secreto de sus ojos", 485.75], [207, "Twelve Monkeys", 400.25], [5, "Pulp Fiction", 392.5], [24, "The Usual Suspects", 391.75], [25, "The Silence of the Lambs", 391.5]], "L\u00e9on": [[5, "Pulp Fiction", 997.5], [24, "The Usual Suspects", 996.75], [25, "The Silence of the Lambs", 996.5], [47, "The Departed", 996.25], [67, "M", 996.25], [153, "Fargo", 995.5], [168, "No Country for Old Men", 995.5], [245, "Rope", 995.25], [146, "V for Vendetta", 910.5], [1, "The Shawshank Redemption", 903.25]], "Forrest Gump": [[29, "La vita \u00e8 bella", 361.5], [30, "Casablanca", 361.5], [34, "City Lights", 361.5], [85, "Eternal Sunshine of the Spotless Mind", 361.0], [98, "The Apartment", 361.0], [159, "Gone with the Wind", 360.5], [178, "Annie Hall", 360.5], [195, "The Best Years of Our Lives", 360.5], [208, "Notorious", 360.25], [217, "Before Sunrise", 360.25]], "Psycho": [[179, "Les diaboliques", 515.5], [36, "Rear Window", 436.5], [62, "North by Northwest", 436.25], [66, "Vertigo", 436.0], [144, "Rebecca", 435.5], [23, "Se7en", 421.75], [41, "Memento", 421.25], [51, "The Prestige", 421.25], [71, "Oldboy", 421.0], [84, "Gone Girl", 421.0]], "The Deer Hunter": [[30, "Casablanca", 601.5], [35, "Saving Private Ryan", 601.5], [42, "The Pianist", 601.25], [45, "Apocalypse Now", 601.25], [52, "The Great Dictator", 601.25], [59, "Paths of Glory", 601.25], [70, "Das Boot", 601.25], [73, "Hotaru no haka", 601.25], [87, "Full Metal Jacket", 601.0], [105, "Inglourious Basterds", 600.75]], "Singin' in the Rain": [[29, "La vita \u00e8 bella", 241.5], [34, "City Lights", 241.5], [65, "Am\u00e9lie", 241.25], [98, "The Apartment", 241.0], [149, "It Happened One Night", 240.75], [178, "Annie Hall", 240.5], [234, "Roman Holiday", 240.25], [235, "The Graduate", 240.25], [15, "Forrest Gump", 147.0], [30, "Casablanca", 146.5]], "The Help": [[1, "The Shawshank Redemption", 418.25], [2, "The Godfather", 418.0], [3, "The Godfather: Part II", 417.75], [5, "Pulp Fiction", 417.5], [7, "Schindler's List", 417.25], [8, "12 Angry Men", 417.25], [10, "Fight Club", 417.25], [15, "Forrest Gump", 417.0], [16, "One Flew Over the Cuckoo's Nest", 417.0], [18, "Goodfellas", 416.75]], "The Wolf of Wall Street": [[18, "Goodfellas", 406.75], [142, "Casino", 405.5], [38, "The Intouchables", 391.5], [90, "The Sting", 391.0], [93, "Snatch.", 390.75], [139, "Lock, Stock and Two Smoking Barrels", 390.5], [143, "The Big Lebowski", 390.5], [170, "Butch Cassidy and the Sundance Kid", 390.5], [246, "Crna macka, beli macor", 390.5], [247, "Papillon", 390.25]], "The Lion King": [[117, "Up", 785.75], [37, "Sen to Chihiro no Kamikakushi", 691.5], [61, "WALL\u00b7E", 691.25], [70, "Das Boot", 691.25], [73, "Hotaru no haka", 691.25], [68, "Toy Story 3", 691.0], [72, "Mononoke-hime", 691.0], [83, "Lawrence of Arabia", 691.0], [103, "The Treasure of the Sierra Madre", 691.0], [105, "Inglourious Basterds", 690.75]], "Network": [[8, "12 Angry Men", 282.25], [221, "Dog Day Afternoon", 280.25], [44, "Sunset Blvd.", 276.5], [116, "Chinatown", 275.75], [126, "The Bridge on the River Kwai", 275.75], [242, "Stalag 17", 275.25], [1, "The Shawshank Redemption", 268.25], [2, "The Godfather", 268.0], [3, "The Godfather: Part II", 267.75], [5, "Pulp Fiction", 267.5]], "The Sting": [[150, "Cool Hand Luke", 340.5], [1, "The Shawshank Redemption", 333.25], [2, "The Godfather", 333.0], [3, "The Godfather: Part II", 332.75], [5, "Pulp Fiction", 332.5], [18, "Goodfellas", 331.75], [22, "City of God", 331.75], [24, "The Usual Suspects", 331.75], [25, "The Silence of the Lambs", 331.5], [28, "L\u00e9on", 331.5]], "The Lord of the Rings: The Return of the King": [[17, "The Lord of the Rings: The Two Towers", 827.0], [11, "The Lord of the Rings: The Fellowship of the Ring", 817.0], [13, "Star Wars: Episode V - The Empire Strikes Back", 782.0], [20, "Star Wars", 781.75], [72, "Mononoke-hime", 781.0], [74, "Star Wars: Episode VI - Return of the Jedi", 781.0], [92, "Monty Python and the Holy Grail", 781.0], [190, "The Wizard of Oz", 780.25], [215, "Harry Potter and the Deathly Hallows: Part 2", 780.25], [227, "Pirates of the Caribbean: The Curse of the Black Pearl", 780.25]], "The Green Mile": [[1, "The Shawshank Redemption", 498.25], [2, "The Godfather", 483.0], [3, "The Godfather: Part II", 482.75], [5, "Pulp Fiction", 482.5], [18, "Goodfellas", 481.75], [22, "City of God", 481.75], [24, "The Usual Suspects", 481.75], [26, "It's a Wonderful Life", 481.75], [25, "The Silence of the Lambs", 481.5], [28, "L\u00e9on", 481.5]], "Yojimbo": [[136, "Ran", 445.75], [35, "Saving Private Ryan", 421.5], [48, "Gladiator", 421.25], [81, "Braveheart", 421.0], [103, "The Treasure of the Sierra Madre", 421.0], [125, "Heat", 420.75], [146, "V for Vendetta", 420.5], [154, "Rush", 420.5], [218, "Yip Man", 420.25], [21, "Seven Samurai", 351.75]], "Modern Times": [[52, "The Great Dictator", 211.25], [34, "City Lights", 201.5], [101, "The Kid", 201.0], [133, "The Gold Rush", 200.75], [29, "La vita \u00e8 bella", 176.5], [38, "The Intouchables", 176.5], [46, "Dr. Strangelove or: How I Learned to Stop Worrying and Love the Bomb", 176.25], [49, "Back to the Future", 176.25], [65, "Am\u00e9lie", 176.25], [124, "3 Idiots", 176.25]], "Lagaan: Once Upon a Time in India": [[56, "The Lion King", 511.25], [70, "Das Boot", 511.25], [83, "Lawrence of Arabia", 511.0], [103, "The Treasure of the Sierra Madre", 511.0], [105, "Inglourious Basterds", 510.75], [117, "Up", 510.75], [119, "The Great Escape", 510.75], [126, "The Bridge on the River Kwai", 510.75], [161, "The Wages of Fear", 510.75], [160, "Into the Wild", 510.5]], "Before Sunrise": [[249, "Before Sunset", 485.25], [15, "Forrest Gump", 452.0], [29, "La vita \u00e8 bella", 451.5], [30, "Casablanca", 451.5], [34, "City Lights", 451.5], [85, "Eternal Sunshine of the Spotless Mind", 451.0], [98, "The Apartment", 451.0], [159, "Gone with the Wind", 450.5], [178, "Annie Hall", 450.5], [195, "The Best Years of Our Lives", 450.5]], "Jurassic Park": [[12, "Interstellar", 212.5], [14, "Inception", 212.0], [40, "T2: Judgment Day", 211.25], [49, "Back to the Future", 211.25], [63, "Aliens", 211.0], [94, "Guardians of the Galaxy", 211.0], [161, "The Wages of Fear", 210.75], [138, "Blade Runner", 210.5], [183, "X-Men: Days of Future Past", 210.5], [194, "The Avengers", 210.5]], "The Matrix": [[14, "Inception", 452.0], [40, "T2: Judgment Day", 451.25], [63, "Aliens", 451.0], [94, "Guardians of the Galaxy", 451.0], [183, "X-Men: Days of Future Past", 450.5], [194, "The Avengers", 450.5], [211, "The Terminator", 450.25], [4, "The Dark Knight", 357.5], [12, "Interstellar", 357.5], [13, "Star Wars: Episode V - The Empire Strikes Back", 357.0]], "Toy Story": [[68, "Toy Story 3", 506.0], [167, "Finding Nemo", 485.5], [224, "Monsters, Inc.", 485.25], [37, "Sen to Chihiro no Kamikakushi", 391.5], [49, "Back to the Future", 391.25], [56, "The Lion King", 391.25], [61, "WALL\u00b7E", 391.25], [72, "Mononoke-hime", 391.0], [92, "Monty Python and the Holy Grail", 391.0], [117, "Up", 390.75]], "Crna macka, beli macor": [[90, "The Sting", 391.0], [93, "Snatch.", 390.75], [128, "The Wolf of Wall Street", 390.75], [139, "Lock, Stock and Two Smoking Barrels", 390.5], [143, "The Big Lebowski", 390.5], [244, "Underground", 310.5], [1, "The Shawshank Redemption", 298.25], [2, "The Godfather", 298.0], [3, "The Godfather: Part II", 297.75], [5, "Pulp Fiction", 297.5]], "Fargo": [[5, "Pulp Fiction", 397.5], [24, "The Usual Suspects", 396.75], [25, "The Silence of the Lambs", 396.5], [28, "L\u00e9on", 396.5], [47, "The Departed", 396.25], [67, "M", 396.25], [168, "No Country for Old Men", 395.5], [245, "Rope", 395.25], [1, "The Shawshank Redemption", 303.25], [2, "The Godfather", 303.0]], "Annie Hall": [[29, "La vita \u00e8 bella", 606.5], [34, "City Lights", 606.5], [98, "The Apartment", 606.0], [234, "Roman Holiday", 605.25], [235, "The Graduate", 605.25], [15, "Forrest Gump", 512.0], [30, "Casablanca", 511.5], [38, "The Intouchables", 511.5], [52, "The Great Dictator", 511.25], [65, "Am\u00e9lie", 511.25]], "Twelve Monkeys": [[23, "Se7en", 851.75], [165, "The Sixth Sense", 850.5], [14, "Inception", 842.0], [33, "Psycho", 841.5], [36, "Rear Window", 841.5], [40, "T2: Judgment Day", 841.25], [41, "Memento", 841.25], [51, "The Prestige", 841.25], [62, "North by Northwest", 841.25], [66, "Vertigo", 841.0]], "The Bridge on the River Kwai": [[70, "Das Boot", 996.25], [105, "Inglourious Basterds", 995.75], [83, "Lawrence of Arabia", 926.0], [186, "Ben-Hur", 910.25], [242, "Stalag 17", 910.25], [30, "Casablanca", 901.5], [35, "Saving Private Ryan", 901.5], [42, "The Pianist", 901.25], [45, "Apocalypse Now", 901.25], [52, "The Great Dictator", 901.25]], "Roman Holiday": [[29, "La vita \u00e8 bella", 726.5], [34, "City Lights", 726.5], [98, "The Apartment", 726.0], [178, "Annie Hall", 725.5], [235, "The Graduate", 725.25], [195, "The Best Years of Our Lives", 645.5], [15, "Forrest Gump", 632.0], [30, "Casablanca", 631.5], [38, "The Intouchables", 631.5], [52, "The Great Dictator", 631.25]], "Dil Chahta Hai": [[124, "3 Idiots", 311.25], [29, "La vita \u00e8 bella", 301.5], [34, "City Lights", 301.5], [38, "The Intouchables", 301.5], [52, "The Great Dictator", 301.25], [90, "The Sting", 301.0], [98, "The Apartment", 301.0], [101, "The Kid", 301.0], [172, "Mary and Max", 300.5], [178, "Annie Hall", 300.5]], "City of God": [[1, "The Shawshank Redemption", 273.25], [2, "The Godfather", 273.0], [3, "The Godfather: Part II", 272.75], [5, "Pulp Fiction", 272.5], [18, "Goodfellas", 271.75], [24, "The Usual Suspects", 271.75], [25, "The Silence of the Lambs", 271.5], [28, "L\u00e9on", 271.5], [32, "American History X", 271.5], [43, "The Green Mile", 271.25]], "Hachi: A Dog's Tale": [[26, "It's a Wonderful Life", 361.75], [115, "Taare Zameen Par", 361.25], [101, "The Kid", 361.0], [1, "The Shawshank Redemption", 268.25], [2, "The Godfather", 268.0], [3, "The Godfather: Part II", 267.75], [5, "Pulp Fiction", 267.5], [7, "Schindler's List", 267.25], [8, "12 Angry Men", 267.25], [10, "Fight Club", 267.25]], "Double Indemnity": [[44, "Sunset Blvd.", 316.5], [86, "Witness for the Prosecution", 316.25], [1, "The Shawshank Redemption", 303.25], [2, "The Godfather", 303.0], [3, "The Godfather: Part II", 302.75], [5, "Pulp Fiction", 302.5], [18, "Goodfellas", 301.75], [22, "City of God", 301.75], [24, "The Usual Suspects", 301.75], [25, "The Silence of the Lambs", 301.5]], "Fa yeung nin wa": [[15, "Forrest Gump", 722.0], [29, "La vita \u00e8 bella", 721.5], [30, "Casablanca", 721.5], [34, "City Lights", 721.5], [85, "Eternal Sunshine of the Spotless Mind", 721.0], [98, "The Apartment", 721.0], [159, "Gone with the Wind", 720.5], [178, "Annie Hall", 720.5], [195, "The Best Years of Our Lives", 720.5], [208, "Notorious", 720.25]], "The Godfather": [[3, "The Godfather: Part II", 237.75], [114, "Scarface", 220.75], [122, "On the Waterfront", 220.75], [125, "Heat", 220.75], [221, "Dog Day Afternoon", 220.25], [1, "The Shawshank Redemption", 213.25], [5, "Pulp Fiction", 212.5], [18, "Goodfellas", 211.75], [22, "City of God", 211.75], [24, "The Usual Suspects", 211.75]], "Raging Bull": [[18, "Goodfellas", 1146.75], [142, "Casino", 1145.5], [7, "Schindler's List", 1112.25], [38, "The Intouchables", 1111.5], [42, "The Pianist", 1111.25], [81, "Braveheart", 1111.0], [83, "Lawrence of Arabia", 1111.0], [91, "Amadeus", 1111.0], [118, "Downfall", 1110.75], [135, "The Elephant Man", 1110.5]], "Mononoke-hime": [[37, "Sen to Chihiro no Kamikakushi", 1126.5], [131, "Tonari no Totoro", 1125.75], [147, "Hauru no ugoku shiro", 1125.5], [201, "Kaze no tani no Naushika", 1125.5], [231, "Tenk\u00fb no shiro Rapyuta", 1125.25], [9, "The Lord of the Rings: The Return of the King", 1112.25], [11, "The Lord of the Rings: The Fellowship of the Ring", 1112.0], [13, "Star Wars: Episode V - The Empire Strikes Back", 1112.0], [17, "The Lord of the Rings: The Two Towers", 1112.0], [20, "Star Wars", 1111.75]], "Heat": [[3, "The Godfather: Part II", 592.75], [2, "The Godfather", 583.0], [18, "Goodfellas", 581.75], [76, "Once Upon a Time in America", 581.0], [77, "Taxi Driver", 581.0], [114, "Scarface", 580.75], [142, "Casino", 580.5], [221, "Dog Day Afternoon", 580.25], [1, "The Shawshank Redemption", 573.25], [5, "Pulp Fiction", 572.5]], "The Shawshank Redemption": [[43, "The Green Mile", 436.25], [2, "The Godfather", 423.0], [3, "The Godfather: Part II", 422.75], [5, "Pulp Fiction", 422.5], [18, "Goodfellas", 421.75], [22, "City of God", 421.75], [24, "The Usual Suspects", 421.75], [25, "The Silence of the Lambs", 421.5], [28, "L\u00e9on", 421.5], [32, "American History X", 421.5]], "Star Wars: Episode V - The Empire Strikes Back": [[20, "Star Wars", 906.75], [74, "Star Wars: Episode VI - Return of the Jedi", 906.0], [227, "Pirates of the Caribbean: The Curse of the Black Pearl", 875.25], [31, "The Raiders of the Lost Ark", 791.5], [106, "Indiana Jones and the Final Crusade", 790.75], [4, "The Dark Knight", 782.5], [9, "The Lord of the Rings: The Return of the King", 782.25], [11, "The Lord of the Rings: The Fellowship of the Ring", 782.0], [17, "The Lord of the Rings: The Two Towers", 782.0], [54, "The Dark Knight Rises", 781.5]], "Strangers on a Train": [[177, "Touch of Evil", 605.5], [219, "The Night of the Hunter", 605.25], [248, "The Killing", 605.25], [245, "Rope", 535.25], [163, "Dial M for Murder", 525.5], [5, "Pulp Fiction", 512.5], [24, "The Usual Suspects", 511.75], [25, "The Silence of the Lambs", 511.5], [28, "L\u00e9on", 511.5], [47, "The Departed", 511.25]], "Batman Begins": [[4, "The Dark Knight", 867.5], [54, "The Dark Knight Rises", 866.5], [13, "Star Wars: Episode V - The Empire Strikes Back", 842.0], [20, "Star Wars", 841.75], [31, "The Raiders of the Lost Ark", 841.5], [63, "Aliens", 841.0], [74, "Star Wars: Episode VI - Return of the Jedi", 841.0], [94, "Guardians of the Galaxy", 841.0], [103, "The Treasure of the Sierra Madre", 841.0], [106, "Indiana Jones and the Final Crusade", 840.75]], "Some Like It Hot": [[98, "The Apartment", 261.0], [242, "Stalag 17", 250.25], [29, "La vita \u00e8 bella", 236.5], [34, "City Lights", 236.5], [38, "The Intouchables", 236.5], [39, "Modern Times", 236.5], [46, "Dr. Strangelove or: How I Learned to Stop Worrying and Love the Bomb", 236.25], [49, "Back to the Future", 236.25], [52, "The Great Dictator", 236.25], [65, "Am\u00e9lie", 236.25]], "Saving Private Ryan": [[136, "Ran", 725.75], [30, "Casablanca", 631.5], [42, "The Pianist", 631.25], [45, "Apocalypse Now", 631.25], [48, "Gladiator", 631.25], [52, "The Great Dictator", 631.25], [59, "Paths of Glory", 631.25], [70, "Das Boot", 631.25], [73, "Hotaru no haka", 631.25], [81, "Braveheart", 631.0]], "Rush": [[81, "Braveheart", 366.0], [218, "Yip Man", 365.25], [162, "A Beautiful Mind", 285.5], [7, "Schindler's List", 272.25], [18, "Goodfellas", 271.75], [35, "Saving Private Ryan", 271.5], [38, "The Intouchables", 271.5], [42, "The Pianist", 271.25], [48, "Gladiator", 271.25], [83, "Lawrence of Arabia", 271.0]], "The Lord of the Rings: The Two Towers": [[9, "The Lord of the Rings: The Return of the King", 587.25], [11, "The Lord of the Rings: The Fellowship of the Ring", 577.0], [13, "Star Wars: Episode V - The Empire Strikes Back", 542.0], [20, "Star Wars", 541.75], [72, "Mononoke-hime", 541.0], [74, "Star Wars: Episode VI - Return of the Jedi", 541.0], [92, "Monty Python and the Holy Grail", 541.0], [190, "The Wizard of Oz", 540.25], [215, "Harry Potter and the Deathly Hallows: Part 2", 540.25], [227, "Pirates of the Caribbean: The Curse of the Black Pearl", 540.25]], "There Will Be Blood": [[193, "In the Name of the Father", 755.25], [1, "The Shawshank Redemption", 748.25], [2, "The Godfather", 748.0], [3, "The Godfather: Part II", 747.75], [5, "Pulp Fiction", 747.5], [7, "Schindler's List", 747.25], [8, "12 Angry Men", 747.25], [10, "Fight Club", 747.25], [15, "Forrest Gump", 747.0], [16, "One Flew Over the Cuckoo's Nest", 747.0]], "Up": [[56, "The Lion King", 486.25], [224, "Monsters, Inc.", 405.25], [37, "Sen to Chihiro no Kamikakushi", 391.5], [61, "WALL\u00b7E", 391.25], [70, "Das Boot", 391.25], [73, "Hotaru no haka", 391.25], [68, "Toy Story 3", 391.0], [72, "Mononoke-hime", 391.0], [83, "Lawrence of Arabia", 391.0], [103, "The Treasure of the Sierra Madre", 391.0]], "The Battle of Algiers": [[1, "The Shawshank Redemption", 453.25], [2, "The Godfather", 453.0], [3, "The Godfather: Part II", 452.75], [5, "Pulp Fiction", 452.5], [7, "Schindler's List", 452.25], [18, "Goodfellas", 451.75], [22, "City of God", 451.75], [24, "The Usual Suspects", 451.75], [25, "The Silence of the Lambs", 451.5], [28, "L\u00e9on", 451.5]], "Trainspotting": [[1, "The Shawshank Redemption", 448.25], [2, "The Godfather", 448.0], [3, "The Godfather: Part II", 447.75], [5, "Pulp Fiction", 447.5], [7, "Schindler's List", 447.25], [8, "12 Angry Men", 447.25], [10, "Fight Club", 447.25], [15, "Forrest Gump", 447.0], [16, "One Flew Over the Cuckoo's Nest", 447.0], [18, "Goodfellas", 446.75]], "Nuovo Cinema Paradiso": [[1, "The Shawshank Redemption", 598.25], [2, "The Godfather", 598.0], [3, "The Godfather: Part II", 597.75], [5, "Pulp Fiction", 597.5], [7, "Schindler's List", 597.25], [8, "12 Angry Men", 597.25], [10, "Fight Club", 597.25], [15, "Forrest Gump", 597.0], [16, "One Flew Over the Cuckoo's Nest", 597.0], [18, "Goodfellas", 596.75]], "Incendies": [[23, "Se7en", 481.75], [30, "Casablanca", 481.5], [35, "Saving Private Ryan", 481.5], [42, "The Pianist", 481.25], [45, "Apocalypse Now", 481.25], [51, "The Prestige", 481.25], [52, "The Great Dictator", 481.25], [59, "Paths of Glory", 481.25], [70, "Das Boot", 481.25], [73, "Hotaru no haka", 481.25]], "In the Name of the Father": [[7, "Schindler's List", 937.25], [118, "Downfall", 935.75], [173, "12 Years a Slave", 935.5], [200, "Gandhi", 935.25], [209, "The King's Speech", 935.25], [18, "Goodfellas", 841.75], [38, "The Intouchables", 841.5], [42, "The Pianist", 841.25], [81, "Braveheart", 841.0], [83, "Lawrence of Arabia", 841.0]], "Downfall": [[7, "Schindler's List", 457.25], [173, "12 Years a Slave", 455.5], [193, "In the Name of the Father", 455.25], [200, "Gandhi", 455.25], [209, "The King's Speech", 455.25], [18, "Goodfellas", 361.75], [38, "The Intouchables", 361.5], [42, "The Pianist", 361.25], [81, "Braveheart", 361.0], [83, "Lawrence of Arabia", 361.0]], "Jaws": [[5, "Pulp Fiction", 482.5], [23, "Se7en", 481.75], [24, "The Usual Suspects", 481.75], [25, "The Silence of the Lambs", 481.5], [28, "L\u00e9on", 481.5], [47, "The Departed", 481.25], [51, "The Prestige", 481.25], [53, "The Lives of Others", 481.25], [67, "M", 481.25], [71, "Oldboy", 481.0]], "Star Wars: Episode VI - Return of the Jedi": [[13, "Star Wars: Episode V - The Empire Strikes Back", 577.0], [20, "Star Wars", 576.75], [227, "Pirates of the Caribbean: The Curse of the Black Pearl", 545.25], [31, "The Raiders of the Lost Ark", 461.5], [106, "Indiana Jones and the Final Crusade", 460.75], [4, "The Dark Knight", 452.5], [9, "The Lord of the Rings: The Return of the King", 452.25], [11, "The Lord of the Rings: The Fellowship of the Ring", 452.0], [17, "The Lord of the Rings: The Two Towers", 452.0], [54, "The Dark Knight Rises", 451.5]], "Bom yeoreum gaeul gyeoul geurigo bom": [[1, "The Shawshank Redemption", 298.25], [2, "The Godfather", 298.0], [3, "The Godfather: Part II", 297.75], [5, "Pulp Fiction", 297.5], [7, "Schindler's List", 297.25], [8, "12 Angry Men", 297.25], [10, "Fight Club", 297.25], [15, "Forrest Gump", 297.0], [16, "One Flew Over the Cuckoo's Nest", 297.0], [18, "Goodfellas", 296.75]], "The Truman Show": [[85, "Eternal Sunshine of the Spotless Mind", 156.0], [162, "A Beautiful Mind", 155.5], [1, "The Shawshank Redemption", 148.25], [2, "The Godfather", 148.0], [3, "The Godfather: Part II", 147.75], [5, "Pulp Fiction", 147.5], [7, "Schindler's List", 147.25], [8, "12 Angry Men", 147.25], [10, "Fight Club", 147.25], [15, "Forrest Gump", 147.0]], "Festen": [[127, "Jagten", 230.75], [1, "The Shawshank Redemption", 208.25], [2, "The Godfather", 208.0], [3, "The Godfather: Part II", 207.75], [5, "Pulp Fiction", 207.5], [7, "Schindler's List", 207.25], [8, "12 Angry Men", 207.25], [10, "Fight Club", 207.25], [15, "Forrest Gump", 207.0], [16, "One Flew Over the Cuckoo's Nest", 207.0]], "Alien": [[166, "The Thing", 390.5], [138, "Blade Runner", 310.5], [63, "Aliens", 306.0], [12, "Interstellar", 297.5], [14, "Inception", 297.0], [19, "The Matrix", 296.75], [33, "Psycho", 296.5], [40, "T2: Judgment Day", 296.25], [49, "Back to the Future", 296.25], [57, "The Shining", 296.25]], "The Third Man": [[177, "Touch of Evil", 880.5], [23, "Se7en", 871.75], [33, "Psycho", 871.5], [36, "Rear Window", 871.5], [41, "Memento", 871.25], [51, "The Prestige", 871.25], [62, "North by Northwest", 871.25], [66, "Vertigo", 871.0], [71, "Oldboy", 871.0], [84, "Gone Girl", 871.0]], "Scarface": [[2, "The Godfather", 343.0], [3, "The Godfather: Part II", 342.75], [125, "Heat", 340.75], [221, "Dog Day Afternoon", 340.25], [1, "The Shawshank Redemption", 333.25], [5, "Pulp Fiction", 332.5], [18, "Goodfellas", 331.75], [22, "City of God", 331.75], [24, "The Usual Suspects", 331.75], [25, "The Silence of the Lambs", 331.5]], "All About Eve": [[1, "The Shawshank Redemption", 238.25], [2, "The Godfather", 238.0], [3, "The Godfather: Part II", 237.75], [5, "Pulp Fiction", 237.5], [7, "Schindler's List", 237.25], [8, "12 Angry Men", 237.25], [10, "Fight Club", 237.25], [15, "Forrest Gump", 237.0], [16, "One Flew Over the Cuckoo's Nest", 237.0], [18, "Goodfellas", 236.75]], "Stalker": [[75, "A Clockwork Orange", 811.0], [85, "Eternal Sunshine of the Spotless Mind", 811.0], [111, "Metropolis", 810.75], [199, "Donnie Darko", 810.25], [238, "Her", 810.25], [1, "The Shawshank Redemption", 718.25], [2, "The Godfather", 718.0], [3, "The Godfather: Part II", 717.75], [5, "Pulp Fiction", 717.5], [12, "Interstellar", 717.5]], "Before Sunset": [[217, "Before Sunrise", 425.25], [15, "Forrest Gump", 392.0], [29, "La vita \u00e8 bella", 391.5], [30, "Casablanca", 391.5], [34, "City Lights", 391.5], [85, "Eternal Sunshine of the Spotless Mind", 391.0], [98, "The Apartment", 391.0], [159, "Gone with the Wind", 390.5], [178, "Annie Hall", 390.5], [195, "The Best Years of Our Lives", 390.5]], "Kaze no tani no Naushika": [[231, "Tenk\u00fb no shiro Rapyuta", 470.25], [37, "Sen to Chihiro no Kamikakushi", 376.5], [72, "Mononoke-hime", 376.0], [147, "Hauru no ugoku shiro", 375.5], [4, "The Dark Knight", 362.5], [13, "Star Wars: Episode V - The Empire Strikes Back", 362.0], [20, "Star Wars", 361.75], [31, "The Raiders of the Lost Ark", 361.5], [54, "The Dark Knight Rises", 361.5], [56, "The Lion King", 361.25]], "Goodfellas": [[142, "Casino", 340.5], [247, "Papillon", 305.25], [113, "Raging Bull", 245.75], [77, "Taxi Driver", 236.0], [47, "The Departed", 226.25], [128, "The Wolf of Wall Street", 225.75], [3, "The Godfather: Part II", 222.75], [76, "Once Upon a Time in America", 221.0], [125, "Heat", 220.75], [1, "The Shawshank Redemption", 213.25]], "For a Fistful of Dollars": [[99, "For a Few Dollars More", 330.75], [6, "The Good, the Bad and the Ugly", 322.5], [27, "Once Upon a Time in the West", 311.75], [112, "Unforgiven", 305.75], [55, "Django Unchained", 296.25], [170, "Butch Cassidy and the Sundance Kid", 295.5], [205, "High Noon", 295.25], [76, "Once Upon a Time in America", 216.0], [141, "Gran Torino", 210.5], [192, "Million Dollar Baby", 210.25]], "Butch Cassidy and the Sundance Kid": [[18, "Goodfellas", 301.75], [128, "The Wolf of Wall Street", 300.75], [142, "Casino", 300.5], [247, "Papillon", 300.25], [90, "The Sting", 241.0], [150, "Cool Hand Luke", 215.5], [1, "The Shawshank Redemption", 208.25], [2, "The Godfather", 208.0], [3, "The Godfather: Part II", 207.75], [5, "Pulp Fiction", 207.5]], "Reservoir Dogs": [[5, "Pulp Fiction", 257.5], [1, "The Shawshank Redemption", 243.25], [2, "The Godfather", 243.0], [3, "The Godfather: Part II", 242.75], [18, "Goodfellas", 241.75], [22, "City of God", 241.75], [24, "The Usual Suspects", 241.75], [25, "The Silence of the Lambs", 241.5], [28, "L\u00e9on", 241.5], [32, "American History X", 241.5]], "Seven Samurai": [[95, "Rash\u00f4mon", 201.0], [108, "Yojimbo", 201.0], [132, "Ikiru", 201.0], [136, "Ran", 190.75], [1, "The Shawshank Redemption", 178.25], [2, "The Godfather", 178.0], [3, "The Godfather: Part II", 177.75], [5, "Pulp Fiction", 177.5], [7, "Schindler's List", 177.25], [8, "12 Angry Men", 177.25]], "American Beauty": [[23, "Se7en", 486.75], [24, "The Usual Suspects", 486.75], [97, "L.A. Confidential", 485.75], [1, "The Shawshank Redemption", 478.25], [2, "The Godfather", 478.0], [3, "The Godfather: Part II", 477.75], [5, "Pulp Fiction", 477.5], [7, "Schindler's List", 477.25], [8, "12 Angry Men", 477.25], [10, "Fight Club", 477.25]], "Her": [[85, "Eternal Sunshine of the Spotless Mind", 426.0], [15, "Forrest Gump", 332.0], [29, "La vita \u00e8 bella", 331.5], [30, "Casablanca", 331.5], [34, "City Lights", 331.5], [75, "A Clockwork Orange", 331.0], [98, "The Apartment", 331.0], [111, "Metropolis", 330.75], [159, "Gone with the Wind", 330.5], [178, "Annie Hall", 330.5]], "8\u00bd": [[26, "It's a Wonderful Life", 331.75], [43, "The Green Mile", 331.25], [123, "Pan's Labyrinth", 330.75], [130, "Det sjunde inseglet", 330.75], [216, "Groundhog Day", 330.25], [222, "La Strada", 250.25], [1, "The Shawshank Redemption", 238.25], [2, "The Godfather", 238.0], [3, "The Godfather: Part II", 237.75], [5, "Pulp Fiction", 237.5]], "Braveheart": [[154, "Rush", 455.5], [218, "Yip Man", 455.25], [7, "Schindler's List", 362.25], [18, "Goodfellas", 361.75], [35, "Saving Private Ryan", 361.5], [38, "The Intouchables", 361.5], [42, "The Pianist", 361.25], [48, "Gladiator", 361.25], [83, "Lawrence of Arabia", 361.0], [91, "Amadeus", 361.0]], "Groundhog Day": [[26, "It's a Wonderful Life", 391.75], [29, "La vita \u00e8 bella", 391.5], [34, "City Lights", 391.5], [38, "The Intouchables", 391.5], [43, "The Green Mile", 391.25], [52, "The Great Dictator", 391.25], [124, "3 Idiots", 391.25], [156, "Dil Chahta Hai", 391.25], [90, "The Sting", 391.0], [92, "Monty Python and the Holy Grail", 391.0]], "Papillon": [[18, "Goodfellas", 786.75], [142, "Casino", 785.5], [1, "The Shawshank Redemption", 693.25], [2, "The Godfather", 693.0], [3, "The Godfather: Part II", 692.75], [5, "Pulp Fiction", 692.5], [7, "Schindler's List", 692.25], [22, "City of God", 691.75], [24, "The Usual Suspects", 691.75], [25, "The Silence of the Lambs", 691.5]], "Django Unchained": [[6, "The Good, the Bad and the Ugly", 417.5], [27, "Once Upon a Time in the West", 416.75], [99, "For a Few Dollars More", 415.75], [112, "Unforgiven", 415.75], [170, "Butch Cassidy and the Sundance Kid", 415.5], [205, "High Noon", 415.25], [230, "For a Fistful of Dollars", 415.25], [5, "Pulp Fiction", 337.5], [79, "Reservoir Dogs", 336.0], [105, "Inglourious Basterds", 335.75]], "The Big Lebowski": [[90, "The Sting", 391.0], [93, "Snatch.", 390.75], [128, "The Wolf of Wall Street", 390.75], [139, "Lock, Stock and Two Smoking Barrels", 390.5], [246, "Crna macka, beli macor", 390.5], [153, "Fargo", 310.5], [224, "Monsters, Inc.", 305.25], [1, "The Shawshank Redemption", 298.25], [2, "The Godfather", 298.0], [3, "The Godfather: Part II", 297.75]], "The Prestige": [[23, "Se7en", 456.75], [71, "Oldboy", 456.0], [84, "Gone Girl", 456.0], [116, "Chinatown", 455.75], [140, "El secreto de sus ojos", 455.75], [165, "The Sixth Sense", 455.5], [41, "Memento", 376.25], [5, "Pulp Fiction", 362.5], [24, "The Usual Suspects", 361.75], [25, "The Silence of the Lambs", 361.5]], "Pulp Fiction": [[24, "The Usual Suspects", 996.75], [25, "The Silence of the Lambs", 996.5], [28, "L\u00e9on", 996.5], [47, "The Departed", 996.25], [67, "M", 996.25], [153, "Fargo", 995.5], [168, "No Country for Old Men", 995.5], [245, "Rope", 995.25], [79, "Reservoir Dogs", 916.0], [1, "The Shawshank Redemption", 903.25]], "Snatch.": [[139, "Lock, Stock and Two Smoking Barrels", 315.5], [90, "The Sting", 301.0], [128, "The Wolf of Wall Street", 300.75], [143, "The Big Lebowski", 300.5], [246, "Crna macka, beli macor", 300.5], [1, "The Shawshank Redemption", 208.25], [2, "The Godfather", 208.0], [3, "The Godfather: Part II", 207.75], [5, "Pulp Fiction", 207.5], [18, "Goodfellas", 206.75]], "Monsters, Inc.": [[68, "Toy Story 3", 486.0], [110, "Toy Story", 485.75], [167, "Finding Nemo", 485.5], [117, "Up", 405.75], [37, "Sen to Chihiro no Kamikakushi", 391.5], [49, "Back to the Future", 391.25], [56, "The Lion King", 391.25], [61, "WALL\u00b7E", 391.25], [72, "Mononoke-hime", 391.0], [92, "Monty Python and the Holy Grail", 391.0]], "Die Hard": [[14, "Inception", 302.0], [40, "T2: Judgment Day", 301.25], [146, "V for Vendetta", 300.5], [197, "The Bourne Ultimatum", 300.25], [165, "The Sixth Sense", 215.5], [180, "Sin City", 215.25], [207, "Twelve Monkeys", 215.25], [4, "The Dark Knight", 207.5], [5, "Pulp Fiction", 207.5], [13, "Star Wars: Episode V - The Empire Strikes Back", 207.0]], "Once Upon a Time in America": [[3, "The Godfather: Part II", 822.75], [18, "Goodfellas", 821.75], [77, "Taxi Driver", 821.0], [125, "Heat", 820.75], [142, "Casino", 820.5], [1, "The Shawshank Redemption", 813.25], [2, "The Godfather", 813.0], [5, "Pulp Fiction", 812.5], [22, "City of God", 811.75], [24, "The Usual Suspects", 811.75]], "The Dark Knight": [[54, "The Dark Knight Rises", 596.5], [109, "Batman Begins", 595.75], [13, "Star Wars: Episode V - The Empire Strikes Back", 572.0], [20, "Star Wars", 571.75], [31, "The Raiders of the Lost Ark", 571.5], [63, "Aliens", 571.0], [74, "Star Wars: Episode VI - Return of the Jedi", 571.0], [94, "Guardians of the Galaxy", 571.0], [103, "The Treasure of the Sierra Madre", 571.0], [106, "Indiana Jones and the Final Crusade", 570.75]], "No Country for Old Men": [[5, "Pulp Fiction", 547.5], [24, "The Usual Suspects", 546.75], [25, "The Silence of the Lambs", 546.5], [28, "L\u00e9on", 546.5], [47, "The Departed", 546.25], [67, "M", 546.25], [153, "Fargo", 545.5], [245, "Rope", 545.25], [1, "The Shawshank Redemption", 453.25], [2, "The Godfather", 453.0]], "V for Vendetta": [[28, "L\u00e9on", 251.5], [5, "Pulp Fiction", 242.5], [14, "Inception", 242.0], [23, "Se7en", 241.75], [24, "The Usual Suspects", 241.75], [25, "The Silence of the Lambs", 241.5], [35, "Saving Private Ryan", 241.5], [40, "T2: Judgment Day", 241.25], [47, "The Departed", 241.25], [48, "Gladiator", 241.25]], "Mr. Smith Goes to Washington": [[26, "It's a Wonderful Life", 381.75], [208, "Notorious", 365.25], [245, "Rope", 365.25], [1, "The Shawshank Redemption", 358.25], [2, "The Godfather", 358.0], [3, "The Godfather: Part II", 357.75], [5, "Pulp Fiction", 357.5], [7, "Schindler's List", 357.25], [8, "12 Angry Men", 357.25], [10, "Fight Club", 357.25]], "Unforgiven": [[6, "The Good, the Bad and the Ugly", 247.5], [99, "For a Few Dollars More", 245.75], [230, "For a Fistful of Dollars", 245.25], [27, "Once Upon a Time in the West", 236.75], [55, "Django Unchained", 236.25], [170, "Butch Cassidy and the Sundance Kid", 235.5], [205, "High Noon", 235.25], [192, "Million Dollar Baby", 175.25], [141, "Gran Torino", 165.5], [1, "The Shawshank Redemption", 153.25]], "Sunset Blvd.": [[78, "Double Indemnity", 316.0], [158, "The Maltese Falcon", 300.5], [208, "Notorious", 300.25], [242, "Stalag 17", 230.25], [86, "Witness for the Prosecution", 221.25], [98, "The Apartment", 221.0], [126, "The Bridge on the River Kwai", 215.75], [176, "Network", 215.5], [1, "The Shawshank Redemption", 208.25], [2, "The Godfather", 208.0]], "12 Angry Men": [[176, "Network", 340.5], [221, "Dog Day Afternoon", 340.25], [122, "On the Waterfront", 335.75], [189, "The Grapes of Wrath", 335.5], [1, "The Shawshank Redemption", 328.25], [2, "The Godfather", 328.0], [3, "The Godfather: Part II", 327.75], [5, "Pulp Fiction", 327.5], [7, "Schindler's List", 327.25], [10, "Fight Club", 327.25]], "Dog Day Afternoon": [[2, "The Godfather", 433.0], [3, "The Godfather: Part II", 432.75], [114, "Scarface", 430.75], [125, "Heat", 430.75], [1, "The Shawshank Redemption", 423.25], [5, "Pulp Fiction", 422.5], [18, "Goodfellas", 421.75], [22, "City of God", 421.75], [24, "The Usual Suspects", 421.75], [25, "The Silence of the Lambs", 421.5]], "X-Men: Days of Future Past": [[63, "Aliens", 666.0], [94, "Guardians of the Galaxy", 666.0], [194, "The Avengers", 665.5], [4, "The Dark Knight", 572.5], [12, "Interstellar", 572.5], [13, "Star Wars: Episode V - The Empire Strikes Back", 572.0], [14, "Inception", 572.0], [19, "The Matrix", 571.75], [20, "Star Wars", 571.75], [31, "The Raiders of the Lost Ark", 571.5]], "Rebecca": [[33, "Psycho", 616.5], [36, "Rear Window", 616.5], [62, "North by Northwest", 616.25], [66, "Vertigo", 616.0], [23, "Se7en", 601.75], [41, "Memento", 601.25], [51, "The Prestige", 601.25], [71, "Oldboy", 601.0], [84, "Gone Girl", 601.0], [104, "The Third Man", 601.0]], "Cool Hand Luke": [[90, "The Sting", 671.0], [1, "The Shawshank Redemption", 663.25], [2, "The Godfather", 663.0], [3, "The Godfather: Part II", 662.75], [5, "Pulp Fiction", 662.5], [18, "Goodfellas", 661.75], [22, "City of God", 661.75], [24, "The Usual Suspects", 661.75], [25, "The Silence of the Lambs", 661.5], [28, "L\u00e9on", 661.5]], "Mou gaan dou": [[5, "Pulp Fiction", 872.5], [23, "Se7en", 871.75], [24, "The Usual Suspects", 871.75], [25, "The Silence of the Lambs", 871.5], [28, "L\u00e9on", 871.5], [33, "Psycho", 871.5], [36, "Rear Window", 871.5], [41, "Memento", 871.25], [47, "The Departed", 871.25], [51, "The Prestige", 871.25]], "Gran Torino": [[192, "Million Dollar Baby", 200.25], [1, "The Shawshank Redemption", 178.25], [2, "The Godfather", 178.0], [3, "The Godfather: Part II", 177.75], [5, "Pulp Fiction", 177.5], [7, "Schindler's List", 177.25], [8, "12 Angry Men", 177.25], [10, "Fight Club", 177.25], [15, "Forrest Gump", 177.0], [16, "One Flew Over the Cuckoo's Nest", 177.0]], "Oldboy": [[23, "Se7en", 876.75], [51, "The Prestige", 876.25], [84, "Gone Girl", 876.0], [116, "Chinatown", 875.75], [140, "El secreto de sus ojos", 875.75], [165, "The Sixth Sense", 875.5], [5, "Pulp Fiction", 782.5], [24, "The Usual Suspects", 781.75], [25, "The Silence of the Lambs", 781.5], [28, "L\u00e9on", 781.5]], "Hauru no ugoku shiro": [[37, "Sen to Chihiro no Kamikakushi", 591.5], [152, "How to Train Your Dragon", 575.5], [72, "Mononoke-hime", 496.0], [131, "Tonari no Totoro", 495.75], [201, "Kaze no tani no Naushika", 495.5], [231, "Tenk\u00fb no shiro Rapyuta", 495.25], [56, "The Lion King", 481.25], [61, "WALL\u00b7E", 481.25], [68, "Toy Story 3", 481.0], [110, "Toy Story", 480.75]], "Sin City": [[5, "Pulp Fiction", 782.5], [24, "The Usual Suspects", 781.75], [25, "The Silence of the Lambs", 781.5], [28, "L\u00e9on", 781.5], [47, "The Departed", 781.25], [67, "M", 781.25], [153, "Fargo", 780.5], [163, "Dial M for Murder", 780.5], [168, "No Country for Old Men", 780.5], [177, "Touch of Evil", 780.5]], "North by Northwest": [[33, "Psycho", 766.5], [36, "Rear Window", 766.5], [66, "Vertigo", 766.0], [144, "Rebecca", 765.5], [23, "Se7en", 751.75], [41, "Memento", 751.25], [51, "The Prestige", 751.25], [71, "Oldboy", 751.0], [84, "Gone Girl", 751.0], [104, "The Third Man", 751.0]], "Schindler's List": [[200, "Gandhi", 525.25], [118, "Downfall", 515.75], [173, "12 Years a Slave", 515.5], [193, "In the Name of the Father", 515.25], [209, "The King's Speech", 515.25], [18, "Goodfellas", 421.75], [38, "The Intouchables", 421.5], [42, "The Pianist", 421.25], [81, "Braveheart", 421.0], [83, "Lawrence of Arabia", 421.0]], "Jagten": [[237, "Festen", 530.25], [1, "The Shawshank Redemption", 508.25], [2, "The Godfather", 508.0], [3, "The Godfather: Part II", 507.75], [5, "Pulp Fiction", 507.5], [7, "Schindler's List", 507.25], [8, "12 Angry Men", 507.25], [10, "Fight Club", 507.25], [15, "Forrest Gump", 507.0], [16, "One Flew Over the Cuckoo's Nest", 507.0]], "Casino": [[18, "Goodfellas", 761.75], [247, "Papillon", 725.25], [113, "Raging Bull", 665.75], [77, "Taxi Driver", 656.0], [47, "The Departed", 646.25], [128, "The Wolf of Wall Street", 645.75], [3, "The Godfather: Part II", 642.75], [76, "Once Upon a Time in America", 641.0], [125, "Heat", 640.75], [1, "The Shawshank Redemption", 633.25]], "Barry Lyndon": [[75, "A Clockwork Orange", 261.0], [59, "Paths of Glory", 251.25], [87, "Full Metal Jacket", 251.0], [1, "The Shawshank Redemption", 238.25], [2, "The Godfather", 238.0], [3, "The Godfather: Part II", 237.75], [5, "Pulp Fiction", 237.5], [7, "Schindler's List", 237.25], [8, "12 Angry Men", 237.25], [10, "Fight Club", 237.25]], "The Thing": [[33, "Psycho", 691.5], [50, "Alien", 691.25], [102, "2001: A Space Odyssey", 690.75], [179, "Les diaboliques", 690.5], [199, "Donnie Darko", 690.25], [207, "Twelve Monkeys", 690.25], [12, "Interstellar", 597.5], [14, "Inception", 597.0], [19, "The Matrix", 596.75], [23, "Se7en", 596.75]], "Shutter Island": [[23, "Se7en", 481.75], [33, "Psycho", 481.5], [36, "Rear Window", 481.5], [41, "Memento", 481.25], [51, "The Prestige", 481.25], [62, "North by Northwest", 481.25], [66, "Vertigo", 481.0], [71, "Oldboy", 481.0], [84, "Gone Girl", 481.0], [104, "The Third Man", 481.0]], "La Strada": [[198, "8\u00bd", 220.5], [83, "Lawrence of Arabia", 216.0], [1, "The Shawshank Redemption", 208.25], [2, "The Godfather", 208.0], [3, "The Godfather: Part II", 207.75], [5, "Pulp Fiction", 207.5], [7, "Schindler's List", 207.25], [8, "12 Angry Men", 207.25], [10, "Fight Club", 207.25], [15, "Forrest Gump", 207.0]], "Rocky": [[113, "Raging Bull", 480.75], [145, "Warrior", 480.5], [192, "Million Dollar Baby", 480.25], [236, "The Hustler", 480.25], [1, "The Shawshank Redemption", 388.25], [2, "The Godfather", 388.0], [3, "The Godfather: Part II", 387.75], [5, "Pulp Fiction", 387.5], [7, "Schindler's List", 387.25], [8, "12 Angry Men", 387.25]], "Pirates of the Caribbean: The Curse of the Black Pearl": [[13, "Star Wars: Episode V - The Empire Strikes Back", 937.0], [20, "Star Wars", 936.75], [74, "Star Wars: Episode VI - Return of the Jedi", 936.0], [11, "The Lord of the Rings: The Fellowship of the Ring", 852.0], [4, "The Dark Knight", 842.5], [9, "The Lord of the Rings: The Return of the King", 842.25], [17, "The Lord of the Rings: The Two Towers", 842.0], [31, "The Raiders of the Lost Ark", 841.5], [54, "The Dark Knight Rises", 841.5], [63, "Aliens", 841.0]], "The Good, the Bad and the Ugly": [[99, "For a Few Dollars More", 750.75], [230, "For a Fistful of Dollars", 740.25], [27, "Once Upon a Time in the West", 731.75], [112, "Unforgiven", 725.75], [55, "Django Unchained", 716.25], [170, "Butch Cassidy and the Sundance Kid", 715.5], [205, "High Noon", 715.25], [76, "Once Upon a Time in America", 636.0], [141, "Gran Torino", 630.5], [192, "Million Dollar Baby", 630.25]], "Star Wars": [[13, "Star Wars: Episode V - The Empire Strikes Back", 787.0], [74, "Star Wars: Episode VI - Return of the Jedi", 786.0], [227, "Pirates of the Caribbean: The Curse of the Black Pearl", 755.25], [31, "The Raiders of the Lost Ark", 671.5], [106, "Indiana Jones and the Final Crusade", 670.75], [4, "The Dark Knight", 662.5], [9, "The Lord of the Rings: The Return of the King", 662.25], [11, "The Lord of the Rings: The Fellowship of the Ring", 662.0], [17, "The Lord of the Rings: The Two Towers", 662.0], [54, "The Dark Knight Rises", 661.5]], "Amores perros": [[5, "Pulp Fiction", 1022.5], [23, "Se7en", 1021.75], [24, "The Usual Suspects", 1021.75], [25, "The Silence of the Lambs", 1021.5], [28, "L\u00e9on", 1021.5], [47, "The Departed", 1021.25], [51, "The Prestige", 1021.25], [53, "The Lives of Others", 1021.25], [67, "M", 1021.25], [71, "Oldboy", 1021.0]], "L.A. Confidential": [[86, "Witness for the Prosecution", 726.25], [95, "Rash\u00f4mon", 726.0], [228, "Salinui chueok", 725.25], [23, "Se7en", 641.75], [24, "The Usual Suspects", 641.75], [1, "The Shawshank Redemption", 633.25], [2, "The Godfather", 633.0], [3, "The Godfather: Part II", 632.75], [5, "Pulp Fiction", 632.5], [18, "Goodfellas", 631.75]], "Paths of Glory": [[87, "Full Metal Jacket", 496.0], [30, "Casablanca", 481.5], [35, "Saving Private Ryan", 481.5], [42, "The Pianist", 481.25], [45, "Apocalypse Now", 481.25], [52, "The Great Dictator", 481.25], [70, "Das Boot", 481.25], [73, "Hotaru no haka", 481.25], [105, "Inglourious Basterds", 480.75], [123, "Pan's Labyrinth", 480.75]], "Apocalypse Now": [[30, "Casablanca", 421.5], [35, "Saving Private Ryan", 421.5], [42, "The Pianist", 421.25], [52, "The Great Dictator", 421.25], [59, "Paths of Glory", 421.25], [70, "Das Boot", 421.25], [73, "Hotaru no haka", 421.25], [87, "Full Metal Jacket", 421.0], [105, "Inglourious Basterds", 420.75], [123, "Pan's Labyrinth", 420.75]], "Mary and Max": [[29, "La vita \u00e8 bella", 721.5], [34, "City Lights", 721.5], [38, "The Intouchables", 721.5], [52, "The Great Dictator", 721.25], [56, "The Lion King", 721.25], [73, "Hotaru no haka", 721.25], [124, "3 Idiots", 721.25], [156, "Dil Chahta Hai", 721.25], [68, "Toy Story 3", 721.0], [90, "The Sting", 721.0]], "Interstellar": [[49, "Back to the Future", 751.25], [63, "Aliens", 751.0], [94, "Guardians of the Galaxy", 751.0], [183, "X-Men: Days of Future Past", 750.5], [194, "The Avengers", 750.5], [240, "Jurassic Park", 750.0], [54, "The Dark Knight Rises", 681.5], [4, "The Dark Knight", 672.5], [14, "Inception", 672.0], [109, "Batman Begins", 670.75]], "Les quatre cents coups": [[1, "The Shawshank Redemption", 723.25], [2, "The Godfather", 723.0], [3, "The Godfather: Part II", 722.75], [5, "Pulp Fiction", 722.5], [18, "Goodfellas", 721.75], [22, "City of God", 721.75], [24, "The Usual Suspects", 721.75], [25, "The Silence of the Lambs", 721.5], [28, "L\u00e9on", 721.5], [32, "American History X", 721.5]], "Rang De Basanti": [[115, "Taare Zameen Par", 426.25], [124, "3 Idiots", 426.25], [156, "Dil Chahta Hai", 426.25], [213, "Lagaan: Once Upon a Time in India", 425.75], [1, "The Shawshank Redemption", 418.25], [2, "The Godfather", 418.0], [3, "The Godfather: Part II", 417.75], [5, "Pulp Fiction", 417.5], [7, "Schindler's List", 417.25], [8, "12 Angry Men", 417.25]], "The Elephant Man": [[7, "Schindler's List", 572.25], [18, "Goodfellas", 571.75], [38, "The Intouchables", 571.5], [42, "The Pianist", 571.25], [81, "Braveheart", 571.0], [83, "Lawrence of Arabia", 571.0], [91, "Amadeus", 571.0], [113, "Raging Bull", 570.75], [118, "Downfall", 570.75], [142, "Casino", 570.5]], "Dr. Strangelove or: How I Learned to Stop Worrying and Love the Bomb": [[52, "The Great Dictator", 481.25], [244, "Underground", 480.5], [242, "Stalag 17", 480.25], [59, "Paths of Glory", 401.25], [87, "Full Metal Jacket", 401.0], [29, "La vita \u00e8 bella", 386.5], [30, "Casablanca", 386.5], [34, "City Lights", 386.5], [35, "Saving Private Ryan", 386.5], [38, "The Intouchables", 386.5]], "Gladiator": [[35, "Saving Private Ryan", 421.5], [81, "Braveheart", 421.0], [103, "The Treasure of the Sierra Madre", 421.0], [108, "Yojimbo", 421.0], [125, "Heat", 420.75], [136, "Ran", 420.75], [146, "V for Vendetta", 420.5], [154, "Rush", 420.5], [218, "Yip Man", 420.25], [97, "L.A. Confidential", 335.75]], "It's a Wonderful Life": [[43, "The Green Mile", 721.25], [115, "Taare Zameen Par", 721.25], [101, "The Kid", 721.0], [123, "Pan's Labyrinth", 720.75], [130, "Det sjunde inseglet", 720.75], [131, "Tonari no Totoro", 720.75], [191, "Hachi: A Dog's Tale", 720.5], [198, "8\u00bd", 720.5], [190, "The Wizard of Oz", 720.25], [216, "Groundhog Day", 720.25]], "Vertigo": [[36, "Rear Window", 716.5], [33, "Psycho", 706.5], [62, "North by Northwest", 706.25], [144, "Rebecca", 705.5], [23, "Se7en", 691.75], [41, "Memento", 691.25], [51, "The Prestige", 691.25], [71, "Oldboy", 691.0], [84, "Gone Girl", 691.0], [104, "The Third Man", 691.0]], "The Kid": [[34, "City Lights", 326.5], [52, "The Great Dictator", 326.25], [26, "It's a Wonderful Life", 301.75], [29, "La vita \u00e8 bella", 301.5], [38, "The Intouchables", 301.5], [115, "Taare Zameen Par", 301.25], [124, "3 Idiots", 301.25], [156, "Dil Chahta Hai", 301.25], [90, "The Sting", 301.0], [98, "The Apartment", 301.0]], "Toy Story 3": [[110, "Toy Story", 655.75], [167, "Finding Nemo", 635.5], [224, "Monsters, Inc.", 635.25], [37, "Sen to Chihiro no Kamikakushi", 541.5], [49, "Back to the Future", 541.25], [56, "The Lion King", 541.25], [61, "WALL\u00b7E", 541.25], [72, "Mononoke-hime", 541.0], [92, "Monty Python and the Holy Grail", 541.0], [117, "Up", 540.75]], "The Godfather: Part II": [[2, "The Godfather", 748.0], [125, "Heat", 740.75], [18, "Goodfellas", 731.75], [76, "Once Upon a Time in America", 731.0], [77, "Taxi Driver", 731.0], [114, "Scarface", 730.75], [142, "Casino", 730.5], [221, "Dog Day Afternoon", 730.25], [1, "The Shawshank Redemption", 723.25], [5, "Pulp Fiction", 722.5]], "Good Will Hunting": [[35, "Saving Private Ryan", 696.5], [47, "The Departed", 696.25], [84, "Gone Girl", 696.0], [1, "The Shawshank Redemption", 688.25], [2, "The Godfather", 688.0], [3, "The Godfather: Part II", 687.75], [5, "Pulp Fiction", 687.5], [7, "Schindler's List", 687.25], [8, "12 Angry Men", 687.25], [10, "Fight Club", 687.25]], "Notorious": [[30, "Casablanca", 551.5], [15, "Forrest Gump", 542.0], [29, "La vita \u00e8 bella", 541.5], [34, "City Lights", 541.5], [44, "Sunset Blvd.", 541.5], [78, "Double Indemnity", 541.0], [85, "Eternal Sunshine of the Spotless Mind", 541.0], [98, "The Apartment", 541.0], [158, "The Maltese Falcon", 540.5], [159, "Gone with the Wind", 540.5]], "Dial M for Murder": [[202, "Strangers on a Train", 855.25], [245, "Rope", 855.25], [5, "Pulp Fiction", 842.5], [24, "The Usual Suspects", 841.75], [25, "The Silence of the Lambs", 841.5], [28, "L\u00e9on", 841.5], [47, "The Departed", 841.25], [67, "M", 841.25], [153, "Fargo", 840.5], [168, "No Country for Old Men", 840.5]], "La vita \u00e8 bella": [[34, "City Lights", 666.5], [98, "The Apartment", 666.0], [178, "Annie Hall", 665.5], [234, "Roman Holiday", 665.25], [235, "The Graduate", 665.25], [15, "Forrest Gump", 572.0], [30, "Casablanca", 571.5], [38, "The Intouchables", 571.5], [52, "The Great Dictator", 571.25], [65, "Am\u00e9lie", 571.25]], "Se7en": [[84, "Gone Girl", 471.0], [51, "The Prestige", 456.25], [71, "Oldboy", 456.0], [116, "Chinatown", 455.75], [140, "El secreto de sus ojos", 455.75], [165, "The Sixth Sense", 455.5], [24, "The Usual Suspects", 371.75], [97, "L.A. Confidential", 370.75], [207, "Twelve Monkeys", 370.25], [5, "Pulp Fiction", 362.5]], "Who's Afraid of Virginia Woolf?": [[235, "The Graduate", 160.25], [1, "The Shawshank Redemption", 148.25], [2, "The Godfather", 148.0], [3, "The Godfather: Part II", 147.75], [5, "Pulp Fiction", 147.5], [7, "Schindler's List", 147.25], [8, "12 Angry Men", 147.25], [10, "Fight Club", 147.25], [15, "Forrest Gump", 147.0], [16, "One Flew Over the Cuckoo's Nest", 147.0]], "Underground": [[52, "The Great Dictator", 696.25], [242, "Stalag 17", 695.25], [29, "La vita \u00e8 bella", 601.5], [30, "Casablanca", 601.5], [34, "City Lights", 601.5], [35, "Saving Private Ryan", 601.5], [38, "The Intouchables", 601.5], [42, "The Pianist", 601.25], [45, "Apocalypse Now", 601.25], [46, "Dr. Strangelove or: How I Learned to Stop Worrying and Love the Bomb", 601.25]], "The Apartment": [[29, "La vita \u00e8 bella", 966.5], [34, "City Lights", 966.5], [178, "Annie Hall", 965.5], [234, "Roman Holiday", 965.25], [235, "The Graduate", 965.25], [242, "Stalag 17", 885.25], [15, "Forrest Gump", 872.0], [30, "Casablanca", 871.5], [38, "The Intouchables", 871.5], [52, "The Great Dictator", 871.25]], "Full Metal Jacket": [[59, "Paths of Glory", 286.25], [30, "Casablanca", 271.5], [35, "Saving Private Ryan", 271.5], [42, "The Pianist", 271.25], [45, "Apocalypse Now", 271.25], [52, "The Great Dictator", 271.25], [70, "Das Boot", 271.25], [73, "Hotaru no haka", 271.25], [105, "Inglourious Basterds", 270.75], [123, "Pan's Labyrinth", 270.75]], "Inglourious Basterds": [[70, "Das Boot", 696.25], [126, "The Bridge on the River Kwai", 695.75], [30, "Casablanca", 601.5], [35, "Saving Private Ryan", 601.5], [42, "The Pianist", 601.25], [45, "Apocalypse Now", 601.25], [52, "The Great Dictator", 601.25], [56, "The Lion King", 601.25], [59, "Paths of Glory", 601.25], [73, "Hotaru no haka", 601.25]], "2001: A Space Odyssey": [[166, "The Thing", 420.5], [199, "Donnie Darko", 420.25], [207, "Twelve Monkeys", 420.25], [75, "A Clockwork Orange", 341.0], [12, "Interstellar", 327.5], [14, "Inception", 327.0], [19, "The Matrix", 326.75], [23, "Se7en", 326.75], [33, "Psycho", 326.5], [36, "Rear Window", 326.5]], "Persona": [[134, "Smultronst\u00e4llet", 500.75], [130, "Det sjunde inseglet", 490.75], [210, "Fanny och Alexander", 490.5], [1, "The Shawshank Redemption", 478.25], [2, "The Godfather", 478.0], [3, "The Godfather: Part II", 477.75], [5, "Pulp Fiction", 477.5], [7, "Schindler's List", 477.25], [8, "12 Angry Men", 477.25], [10, "Fight Club", 477.25]], "Det sjunde inseglet": [[26, "It's a Wonderful Life", 901.75], [43, "The Green Mile", 901.25], [123, "Pan's Labyrinth", 900.75], [198, "8\u00bd", 900.5], [216, "Groundhog Day", 900.25], [134, "Smultronst\u00e4llet", 820.75], [196, "Persona", 820.5], [210, "Fanny och Alexander", 820.5], [1, "The Shawshank Redemption", 808.25], [2, "The Godfather", 808.0]], "For a Few Dollars More": [[6, "The Good, the Bad and the Ugly", 392.5], [230, "For a Fistful of Dollars", 390.25], [27, "Once Upon a Time in the West", 371.75], [112, "Unforgiven", 365.75], [4, "The Dark Knight", 357.5], [13, "Star Wars: Episode V - The Empire Strikes Back", 357.0], [14, "Inception", 357.0], [19, "The Matrix", 356.75], [20, "Star Wars", 356.75], [31, "The Raiders of the Lost Ark", 356.5]], "Smultronst\u00e4llet": [[196, "Persona", 560.5], [130, "Det sjunde inseglet", 550.75], [210, "Fanny och Alexander", 550.5], [1, "The Shawshank Redemption", 538.25], [2, "The Godfather", 538.0], [3, "The Godfather: Part II", 537.75], [5, "Pulp Fiction", 537.5], [7, "Schindler's List", 537.25], [8, "12 Angry Men", 537.25], [10, "Fight Club", 537.25]], "Judgment at Nuremberg": [[164, "Hotel Rwanda", 305.5], [7, "Schindler's List", 212.25], [30, "Casablanca", 211.5], [35, "Saving Private Ryan", 211.5], [42, "The Pianist", 211.25], [45, "Apocalypse Now", 211.25], [52, "The Great Dictator", 211.25], [59, "Paths of Glory", 211.25], [70, "Das Boot", 211.25], [73, "Hotaru no haka", 211.25]], "A Clockwork Orange": [[1, "The Shawshank Redemption", 543.25], [2, "The Godfather", 543.0], [3, "The Godfather: Part II", 542.75], [5, "Pulp Fiction", 542.5], [18, "Goodfellas", 541.75], [22, "City of God", 541.75], [24, "The Usual Suspects", 541.75], [25, "The Silence of the Lambs", 541.5], [28, "L\u00e9on", 541.5], [32, "American History X", 541.5]], "The Usual Suspects": [[5, "Pulp Fiction", 427.5], [25, "The Silence of the Lambs", 426.5], [28, "L\u00e9on", 426.5], [47, "The Departed", 426.25], [67, "M", 426.25], [153, "Fargo", 425.5], [168, "No Country for Old Men", 425.5], [245, "Rope", 425.25], [23, "Se7en", 341.75], [97, "L.A. Confidential", 340.75]], "The Hustler": [[113, "Raging Bull", 240.75], [145, "Warrior", 240.5], [192, "Million Dollar Baby", 240.25], [220, "Rocky", 240.25], [90, "The Sting", 156.0], [150, "Cool Hand Luke", 155.5], [1, "The Shawshank Redemption", 148.25], [2, "The Godfather", 148.0], [3, "The Godfather: Part II", 147.75], [5, "Pulp Fiction", 147.5]], "Amadeus": [[7, "Schindler's List", 302.25], [18, "Goodfellas", 301.75], [38, "The Intouchables", 301.5], [42, "The Pianist", 301.25], [81, "Braveheart", 301.0], [83, "Lawrence of Arabia", 301.0], [113, "Raging Bull", 300.75], [118, "Downfall", 300.75], [135, "The Elephant Man", 300.5], [142, "Casino", 300.5]], "The Great Dictator": [[244, "Underground", 485.5], [242, "Stalag 17", 485.25], [34, "City Lights", 416.5], [101, "The Kid", 416.0], [29, "La vita \u00e8 bella", 391.5], [30, "Casablanca", 391.5], [35, "Saving Private Ryan", 391.5], [38, "The Intouchables", 391.5], [42, "The Pianist", 391.25], [45, "Apocalypse Now", 391.25]], "WALL\u00b7E": [[167, "Finding Nemo", 285.5], [37, "Sen to Chihiro no Kamikakushi", 271.5], [56, "The Lion King", 271.25], [68, "Toy Story 3", 271.0], [72, "Mononoke-hime", 271.0], [110, "Toy Story", 270.75], [117, "Up", 270.75], [147, "Hauru no ugoku shiro", 270.5], [152, "How to Train Your Dragon", 270.5], [201, "Kaze no tani no Naushika", 270.5]], "Touch of Evil": [[202, "Strangers on a Train", 545.25], [219, "The Night of the Hunter", 545.25], [248, "The Killing", 545.25], [104, "The Third Man", 461.0], [5, "Pulp Fiction", 452.5], [24, "The Usual Suspects", 451.75], [25, "The Silence of the Lambs", 451.5], [28, "L\u00e9on", 451.5], [47, "The Departed", 451.25], [67, "M", 451.25]], "Eternal Sunshine of the Spotless Mind": [[238, "Her", 785.25], [15, "Forrest Gump", 692.0], [29, "La vita \u00e8 bella", 691.5], [30, "Casablanca", 691.5], [34, "City Lights", 691.5], [75, "A Clockwork Orange", 691.0], [98, "The Apartment", 691.0], [111, "Metropolis", 690.75], [159, "Gone with the Wind", 690.5], [178, "Annie Hall", 690.5]], "Memento": [[51, "The Prestige", 1006.25], [23, "Se7en", 991.75], [33, "Psycho", 991.5], [36, "Rear Window", 991.5], [62, "North by Northwest", 991.25], [66, "Vertigo", 991.0], [71, "Oldboy", 991.0], [84, "Gone Girl", 991.0], [104, "The Third Man", 991.0], [116, "Chinatown", 990.75]], "The Wages of Fear": [[5, "Pulp Fiction", 662.5], [23, "Se7en", 661.75], [24, "The Usual Suspects", 661.75], [25, "The Silence of the Lambs", 661.5], [28, "L\u00e9on", 661.5], [47, "The Departed", 661.25], [51, "The Prestige", 661.25], [53, "The Lives of Others", 661.25], [56, "The Lion King", 661.25], [67, "M", 661.25]], "Finding Nemo": [[68, "Toy Story 3", 786.0], [110, "Toy Story", 785.75], [224, "Monsters, Inc.", 785.25], [61, "WALL\u00b7E", 706.25], [37, "Sen to Chihiro no Kamikakushi", 691.5], [49, "Back to the Future", 691.25], [56, "The Lion King", 691.25], [72, "Mononoke-hime", 691.0], [92, "Monty Python and the Holy Grail", 691.0], [117, "Up", 690.75]], "Beauty and the Beast": [[131, "Tonari no Totoro", 785.75], [26, "It's a Wonderful Life", 691.75], [37, "Sen to Chihiro no Kamikakushi", 691.5], [72, "Mononoke-hime", 691.0], [147, "Hauru no ugoku shiro", 690.5], [152, "How to Train Your Dragon", 690.5], [190, "The Wizard of Oz", 690.25], [9, "The Lord of the Rings: The Return of the King", 597.25], [11, "The Lord of the Rings: The Fellowship of the Ring", 597.0], [13, "Star Wars: Episode V - The Empire Strikes Back", 597.0]], "Warrior": [[113, "Raging Bull", 630.75], [192, "Million Dollar Baby", 630.25], [220, "Rocky", 630.25], [236, "The Hustler", 630.25], [1, "The Shawshank Redemption", 538.25], [2, "The Godfather", 538.0], [3, "The Godfather: Part II", 537.75], [5, "Pulp Fiction", 537.5], [7, "Schindler's List", 537.25], [8, "12 Angry Men", 537.25]], "Fight Club": [[23, "Se7en", 321.75], [84, "Gone Girl", 311.0], [32, "American History X", 306.5], [105, "Inglourious Basterds", 305.75], [209, "The King's Speech", 305.25], [1, "The Shawshank Redemption", 298.25], [2, "The Godfather", 298.0], [3, "The Godfather: Part II", 297.75], [5, "Pulp Fiction", 297.5], [7, "Schindler's List", 297.25]], "Chinatown": [[23, "Se7en", 726.75], [51, "The Prestige", 726.25], [71, "Oldboy", 726.0], [84, "Gone Girl", 726.0], [140, "El secreto de sus ojos", 725.75], [165, "The Sixth Sense", 725.5], [47, "The Departed", 641.25], [5, "Pulp Fiction", 632.5], [24, "The Usual Suspects", 631.75], [25, "The Silence of the Lambs", 631.5]], "T2: Judgment Day": [[14, "Inception", 907.0], [211, "The Terminator", 845.25], [63, "Aliens", 826.0], [19, "The Matrix", 811.75], [94, "Guardians of the Galaxy", 811.0], [120, "Die Hard", 810.75], [138, "Blade Runner", 810.5], [146, "V for Vendetta", 810.5], [183, "X-Men: Days of Future Past", 810.5], [194, "The Avengers", 810.5]], "The Big Sleep": [[158, "The Maltese Falcon", 790.5], [86, "Witness for the Prosecution", 781.25], [78, "Double Indemnity", 781.0], [95, "Rash\u00f4mon", 781.0], [104, "The Third Man", 781.0], [97, "L.A. Confidential", 780.75], [177, "Touch of Evil", 780.5], [202, "Strangers on a Train", 780.25], [203, "Mou gaan dou", 780.25], [219, "The Night of the Hunter", 780.25]], "M": [[5, "Pulp Fiction", 607.5], [24, "The Usual Suspects", 606.75], [25, "The Silence of the Lambs", 606.5], [28, "L\u00e9on", 606.5], [47, "The Departed", 606.25], [153, "Fargo", 605.5], [168, "No Country for Old Men", 605.5], [245, "Rope", 605.25], [1, "The Shawshank Redemption", 513.25], [2, "The Godfather", 513.0]], "3 Idiots": [[156, "Dil Chahta Hai", 971.25], [29, "La vita \u00e8 bella", 961.5], [34, "City Lights", 961.5], [38, "The Intouchables", 961.5], [52, "The Great Dictator", 961.25], [90, "The Sting", 961.0], [98, "The Apartment", 961.0], [101, "The Kid", 961.0], [172, "Mary and Max", 960.5], [178, "Annie Hall", 960.5]], "The Lord of the Rings: The Fellowship of the Ring": [[9, "The Lord of the Rings: The Return of the King", 607.25], [17, "The Lord of the Rings: The Two Towers", 607.0], [227, "Pirates of the Caribbean: The Curse of the Black Pearl", 580.25], [13, "Star Wars: Episode V - The Empire Strikes Back", 572.0], [20, "Star Wars", 571.75], [72, "Mononoke-hime", 571.0], [74, "Star Wars: Episode VI - Return of the Jedi", 571.0], [92, "Monty Python and the Holy Grail", 571.0], [190, "The Wizard of Oz", 570.25], [215, "Harry Potter and the Deathly Hallows: Part 2", 570.25]], "The Grapes of Wrath": [[8, "12 Angry Men", 427.25], [1, "The Shawshank Redemption", 418.25], [2, "The Godfather", 418.0], [3, "The Godfather: Part II", 417.75], [5, "Pulp Fiction", 417.5], [7, "Schindler's List", 417.25], [10, "Fight Club", 417.25], [15, "Forrest Gump", 417.0], [16, "One Flew Over the Cuckoo's Nest", 417.0], [18, "Goodfellas", 416.75]], "Rope": [[5, "Pulp Fiction", 1087.5], [24, "The Usual Suspects", 1086.75], [25, "The Silence of the Lambs", 1086.5], [28, "L\u00e9on", 1086.5], [47, "The Departed", 1086.25], [67, "M", 1086.25], [153, "Fargo", 1085.5], [168, "No Country for Old Men", 1085.5], [202, "Strangers on a Train", 1015.25], [163, "Dial M for Murder", 1005.5]], "High Noon": [[6, "The Good, the Bad and the Ugly", 327.5], [27, "Once Upon a Time in the West", 326.75], [55, "Django Unchained", 326.25], [99, "For a Few Dollars More", 325.75], [112, "Unforgiven", 325.75], [170, "Butch Cassidy and the Sundance Kid", 325.5], [230, "For a Fistful of Dollars", 325.25], [36, "Rear Window", 241.5], [159, "Gone with the Wind", 240.5], [163, "Dial M for Murder", 240.5]], "Into the Wild": [[83, "Lawrence of Arabia", 1176.0], [7, "Schindler's List", 1082.25], [18, "Goodfellas", 1081.75], [38, "The Intouchables", 1081.5], [42, "The Pianist", 1081.25], [56, "The Lion King", 1081.25], [70, "Das Boot", 1081.25], [81, "Braveheart", 1081.0], [91, "Amadeus", 1081.0], [103, "The Treasure of the Sierra Madre", 1081.0]], "Gandhi": [[7, "Schindler's List", 347.25], [118, "Downfall", 335.75], [173, "12 Years a Slave", 335.5], [193, "In the Name of the Father", 335.25], [209, "The King's Speech", 335.25], [18, "Goodfellas", 241.75], [38, "The Intouchables", 241.5], [42, "The Pianist", 241.25], [81, "Braveheart", 241.0], [83, "Lawrence of Arabia", 241.0]], "Jodaeiye Nader az Simin": [[1, "The Shawshank Redemption", 958.25], [2, "The Godfather", 958.0], [3, "The Godfather: Part II", 957.75], [5, "Pulp Fiction", 957.5], [7, "Schindler's List", 957.25], [8, "12 Angry Men", 957.25], [10, "Fight Club", 957.25], [15, "Forrest Gump", 957.0], [16, "One Flew Over the Cuckoo's Nest", 957.0], [18, "Goodfellas", 956.75]], "On the Waterfront": [[2, "The Godfather", 283.0], [1, "The Shawshank Redemption", 273.25], [3, "The Godfather: Part II", 272.75], [5, "Pulp Fiction", 272.5], [18, "Goodfellas", 271.75], [22, "City of God", 271.75], [24, "The Usual Suspects", 271.75], [25, "The Silence of the Lambs", 271.5], [28, "L\u00e9on", 271.5], [32, "American History X", 271.5]], "How to Train Your Dragon": [[37, "Sen to Chihiro no Kamikakushi", 696.5], [147, "Hauru no ugoku shiro", 695.5], [56, "The Lion King", 601.25], [61, "WALL\u00b7E", 601.25], [68, "Toy Story 3", 601.0], [72, "Mononoke-hime", 601.0], [110, "Toy Story", 600.75], [117, "Up", 600.75], [131, "Tonari no Totoro", 600.75], [167, "Finding Nemo", 600.5]], "Harry Potter and the Deathly Hallows: Part 2": [[9, "The Lord of the Rings: The Return of the King", 512.25], [11, "The Lord of the Rings: The Fellowship of the Ring", 512.0], [13, "Star Wars: Episode V - The Empire Strikes Back", 512.0], [17, "The Lord of the Rings: The Two Towers", 512.0], [20, "Star Wars", 511.75], [72, "Mononoke-hime", 511.0], [74, "Star Wars: Episode VI - Return of the Jedi", 511.0], [92, "Monty Python and the Holy Grail", 511.0], [190, "The Wizard of Oz", 510.25], [227, "Pirates of the Caribbean: The Curse of the Black Pearl", 510.25]], "Hotaru no haka": [[30, "Casablanca", 421.5], [35, "Saving Private Ryan", 421.5], [42, "The Pianist", 421.25], [45, "Apocalypse Now", 421.25], [52, "The Great Dictator", 421.25], [56, "The Lion King", 421.25], [59, "Paths of Glory", 421.25], [70, "Das Boot", 421.25], [87, "Full Metal Jacket", 421.0], [105, "Inglourious Basterds", 420.75]], "The Lives of Others": [[5, "Pulp Fiction", 632.5], [23, "Se7en", 631.75], [24, "The Usual Suspects", 631.75], [25, "The Silence of the Lambs", 631.5], [28, "L\u00e9on", 631.5], [47, "The Departed", 631.25], [51, "The Prestige", 631.25], [67, "M", 631.25], [71, "Oldboy", 631.0], [84, "Gone Girl", 631.0]], "Boyhood": [[217, "Before Sunrise", 590.25], [249, "Before Sunset", 590.25], [1, "The Shawshank Redemption", 568.25], [2, "The Godfather", 568.0], [3, "The Godfather: Part II", 567.75], [5, "Pulp Fiction", 567.5], [7, "Schindler's List", 567.25], [8, "12 Angry Men", 567.25], [10, "Fight Club", 567.25], [15, "Forrest Gump", 567.0]], "Das Boot": [[105, "Inglourious Basterds", 425.75], [126, "The Bridge on the River Kwai", 425.75], [30, "Casablanca", 331.5], [35, "Saving Private Ryan", 331.5], [42, "The Pianist", 331.25], [45, "Apocalypse Now", 331.25], [52, "The Great Dictator", 331.25], [56, "The Lion King", 331.25], [59, "Paths of Glory", 331.25], [73, "Hotaru no haka", 331.25]], "Monty Python and the Holy Grail": [[9, "The Lord of the Rings: The Return of the King", 302.25], [11, "The Lord of the Rings: The Fellowship of the Ring", 302.0], [13, "Star Wars: Episode V - The Empire Strikes Back", 302.0], [17, "The Lord of the Rings: The Two Towers", 302.0], [20, "Star Wars", 301.75], [49, "Back to the Future", 301.25], [68, "Toy Story 3", 301.0], [72, "Mononoke-hime", 301.0], [74, "Star Wars: Episode VI - Return of the Jedi", 301.0], [110, "Toy Story", 300.75]], "The Pianist": [[7, "Schindler's List", 332.25], [18, "Goodfellas", 331.75], [30, "Casablanca", 331.5], [35, "Saving Private Ryan", 331.5], [38, "The Intouchables", 331.5], [45, "Apocalypse Now", 331.25], [52, "The Great Dictator", 331.25], [59, "Paths of Glory", 331.25], [70, "Das Boot", 331.25], [73, "Hotaru no haka", 331.25]], "The Dark Knight Rises": [[4, "The Dark Knight", 987.5], [109, "Batman Begins", 985.75], [13, "Star Wars: Episode V - The Empire Strikes Back", 962.0], [20, "Star Wars", 961.75], [31, "The Raiders of the Lost Ark", 961.5], [63, "Aliens", 961.0], [74, "Star Wars: Episode VI - Return of the Jedi", 961.0], [94, "Guardians of the Galaxy", 961.0], [103, "The Treasure of the Sierra Madre", 961.0], [106, "Indiana Jones and the Final Crusade", 960.75]], "Guardians of the Galaxy": [[63, "Aliens", 906.0], [183, "X-Men: Days of Future Past", 905.5], [194, "The Avengers", 905.5], [4, "The Dark Knight", 812.5], [12, "Interstellar", 812.5], [13, "Star Wars: Episode V - The Empire Strikes Back", 812.0], [14, "Inception", 812.0], [19, "The Matrix", 811.75], [20, "Star Wars", 811.75], [31, "The Raiders of the Lost Ark", 811.5]], "The Departed": [[5, "Pulp Fiction", 637.5], [24, "The Usual Suspects", 636.75], [25, "The Silence of the Lambs", 636.5], [28, "L\u00e9on", 636.5], [67, "M", 636.25], [153, "Fargo", 635.5], [168, "No Country for Old Men", 635.5], [245, "Rope", 635.25], [18, "Goodfellas", 556.75], [77, "Taxi Driver", 556.0]], "Million Dollar Baby": [[113, "Raging Bull", 240.75], [145, "Warrior", 240.5], [220, "Rocky", 240.25], [236, "The Hustler", 240.25], [141, "Gran Torino", 170.5], [1, "The Shawshank Redemption", 158.25], [23, "Se7en", 156.75], [2, "The Godfather", 148.0], [3, "The Godfather: Part II", 147.75], [5, "Pulp Fiction", 147.5]], "One Flew Over the Cuckoo's Nest": [[91, "Amadeus", 191.0], [47, "The Departed", 186.25], [116, "Chinatown", 185.75], [1, "The Shawshank Redemption", 178.25], [2, "The Godfather", 178.0], [3, "The Godfather: Part II", 177.75], [5, "Pulp Fiction", 177.5], [7, "Schindler's List", 177.25], [8, "12 Angry Men", 177.25], [10, "Fight Club", 177.25]], "The Bourne Ultimatum": [[47, "The Departed", 791.25], [5, "Pulp Fiction", 782.5], [14, "Inception", 782.0], [24, "The Usual Suspects", 781.75], [25, "The Silence of the Lambs", 781.5], [28, "L\u00e9on", 781.5], [40, "T2: Judgment Day", 781.25], [67, "M", 781.25], [120, "Die Hard", 780.75], [125, "Heat", 780.75]], "The General": [[4, "The Dark Knight", 302.5], [13, "Star Wars: Episode V - The Empire Strikes Back", 302.0], [20, "Star Wars", 301.75], [31, "The Raiders of the Lost Ark", 301.5], [54, "The Dark Knight Rises", 301.5], [49, "Back to the Future", 301.25], [63, "Aliens", 301.0], [68, "Toy Story 3", 301.0], [74, "Star Wars: Episode VI - Return of the Jedi", 301.0], [92, "Monty Python and the Holy Grail", 301.0]], "Ladri di biciclette": [[1, "The Shawshank Redemption", 478.25], [2, "The Godfather", 478.0], [3, "The Godfather: Part II", 477.75], [5, "Pulp Fiction", 477.5], [7, "Schindler's List", 477.25], [8, "12 Angry Men", 477.25], [10, "Fight Club", 477.25], [15, "Forrest Gump", 477.0], [16, "One Flew Over the Cuckoo's Nest", 477.0], [18, "Goodfellas", 476.75]], "To Kill a Mockingbird": [[234, "Roman Holiday", 275.25], [1, "The Shawshank Redemption", 268.25], [2, "The Godfather", 268.0], [3, "The Godfather: Part II", 267.75], [5, "Pulp Fiction", 267.5], [7, "Schindler's List", 267.25], [8, "12 Angry Men", 267.25], [10, "Fight Club", 267.25], [15, "Forrest Gump", 267.0], [16, "One Flew Over the Cuckoo's Nest", 267.0]], "Ikiru": [[21, "Seven Samurai", 1041.75], [95, "Rash\u00f4mon", 1031.0], [108, "Yojimbo", 1031.0], [136, "Ran", 1030.75], [1, "The Shawshank Redemption", 1018.25], [2, "The Godfather", 1018.0], [3, "The Godfather: Part II", 1017.75], [5, "Pulp Fiction", 1017.5], [7, "Schindler's List", 1017.25], [8, "12 Angry Men", 1017.25]], "Sen to Chihiro no Kamikakushi": [[147, "Hauru no ugoku shiro", 1010.5], [152, "How to Train Your Dragon", 995.5], [72, "Mononoke-hime", 916.0], [131, "Tonari no Totoro", 915.75], [201, "Kaze no tani no Naushika", 915.5], [231, "Tenk\u00fb no shiro Rapyuta", 915.25], [56, "The Lion King", 901.25], [61, "WALL\u00b7E", 901.25], [68, "Toy Story 3", 901.0], [110, "Toy Story", 900.75]], "The Treasure of the Sierra Madre": [[4, "The Dark Knight", 572.5], [13, "Star Wars: Episode V - The Empire Strikes Back", 572.0], [20, "Star Wars", 571.75], [31, "The Raiders of the Lost Ark", 571.5], [35, "Saving Private Ryan", 571.5], [54, "The Dark Knight Rises", 571.5], [48, "Gladiator", 571.25], [56, "The Lion King", 571.25], [70, "Das Boot", 571.25], [63, "Aliens", 571.0]]}